Workbook

Sheet BALANCE Y ESTADO DE RESULTADOS
B2: ESTADO DE RESULTADOS | K2: ANALISIS
B3: INGRESO | F3: EGRESOS | K3: ¿Cuanto dinero retiene?
B4: Ingreso Ganado | F4: Gastos | K4: Flujo de caja neto/Total ingresos | L4: =D27/D19 -> 0.57773065
C5: Salario neto | D5: 8500000 | E5: =D5*100%/$D$19 -> 0.90137858 | G5: Arriendo / Hipoteca | H5: =GASTOS!C3 -> 1700000 | I5: =H5*100%/$H$27 -> 0.42692115
C6: Bonificaciones | D6: 0 | E6: =D6*100%/$D$19 -> 0 | G6: Servicios públicos | H6: =GASTOS!C4 -> 370000 | I6: =H6*100%/$H$27 -> 0.092918132 | K6: ¿Su dinero trabaja para usted?
C7: Honorarios | D7: 0 | E7: =D7*100%/$D$19 -> 0 | G7: Mercado | H7: =GASTOS!C16 -> 600000 | I7: =H7*100%/$H$27 -> 0.15067805 | K7: Ingreso Pasivo y Portafolio/Ingreso Total | L7: =(D13+D18)/D19 -> 0.098621421
C8: Comisiones | D8: 0 | E8: =D8*100%/$D$19 -> 0 | G8: Gastos vivienda | H8: =GASTOS!C11 -> 70000 | I8: =H8*100%/$H$27 -> 0.017579106
B9: Total ingreso ganado | D9: =SUM(D5:D8) -> 8500000 | E9: =SUM(E5:E8) -> 0.90137858 | G9: Gastos vehículo | H9: =GASTOS!C17 -> 0 | I9: =H9*100%/$H$27 -> 0 | K9: ¿Cuánto gasta en su vivienda?
B10: Ingreso pasivo | G10: Gastos hijos | H10: =GASTOS!C19 -> 610000 | I10: =H10*100%/$H$27 -> 0.15318935 | K10: Arriendo+Gastos+Serv publicos/ Ingreso Total | L10: =(H5+H6+H8)/D19 -> 0.22693531
C11: Finca Raiz | D11: 900000 | E11: =D11*100%/$D$19 -> 0.095440085 | G11: Gastos conyuge | H11: =GASTOS!C26 -> 0 | I11: =H11*100%/$H$27 -> 0 | K11: * mantener en menos de 30%
C12: Negocios | D12: 0 | E12: =D12*100%/$D$19 -> 0 | G12: Gastos personales | H12: =GASTOS!G39 -> 106000 | I12: =H12*100%/$H$27 -> 0.026619789
B13: Total ingreso pasivo | D13: =SUM(D11:D12) -> 900000 | E13: =SUM(E11:E12) -> 0.095440085 | G13: Créditos | H13: =GASTOS!C27 -> 350000 | I13: =H13*100%/$H$27 -> 0.08789553 | K13: ¿Cuánto gasta en posesiones?
B14: Ingreso de Portafolio | G14: Gastos bancarios | H14: =GASTOS!C41 -> 16000 | I14: =H14*100%/$H$27 -> 0.0040180814 | K14: Total posesiones/activos Dian-bancos | L14: =D50/D52 -> 0.42972872
C15: Intereses | D15: 0 | E15: =D15*100%/$D$19 -> 0 | G15: Provisión impuestos | H15: =GASTOS!G3 -> 0 | I15: =H15*100%/$H$27 -> 0 | K15: *mantener en menos de 30%
C16: Dividendos | D16: 30000 | E16: =D16*100%/$D$19 -> 0.0031813362 | G16: Provisión seguros | H16: =GASTOS!G7 -> 0 | I16: =H16*100%/$H$27 -> 0
C17: Regalias | D17: 0 | E17: =D17*100%/$D$19 -> 0 | G17: Deportes | H17: =GASTOS!G12 -> 0 | I17: =H17*100%/$H$27 -> 0 | K17: Independencia financiera
B18: Total ingreso de portafolio | D18: =SUM(D15:D17) -> 30000 | E18: =SUM(E15:E17) -> 0.0031813362 | G18: Entretenimiento | H18: =GASTOS!G13 -> 60000 | I18: =H18*100%/$H$27 -> 0.015067805 | K18: Patrimonio neto Dian-bancos/Total gastos | L18: =H52/H27 -> 342.93069
B19: TOTAL INGRESOS | D19: =D9+D13+D18 -> 9430000 | E19: =E9+E13+E18 -> 1 | G19: Sociales | H19: =GASTOS!G19 -> 50000 | I19: =H19*100%/$H$27 -> 0.012556504 | K19: *expresada en meses
G20: Imprevistos | H20: =GASTOS!G50 -> 50000 | I20: =H20*100%/$H$27 -> 0.012556504
G21: Mascota | H21: =GASTOS!G24 -> 0 | I21: =H21*100%/$H$27 -> 0
G22: Ahorro e inversión | H22: =GASTOS!G30 -> 0 | I22: =H22*100%/$H$27 -> 0
G23: Servicio domestico | H23: =GASTOS!G31 -> 0 | I23: =H23*100%/$H$27 -> 0
G24: Salud | H24: =GASTOS!G35 -> 0 | I24: =H24*100%/$H$27 -> 0
G25: Donaciones | H25: =GASTOS!G49 -> 0 | I25: =H25*100%/$H$27 -> 0
G26: Otros | H26: =GASTOS!G51 -> 0 | I26: =H26*100%/$H$27 -> 0
B27: FLUJO DE CAJA NETO | D27: =D19-H27 -> 5448000 | F27: TOTAL GASTOS | H27: =SUM(H5:H26) -> 3982000 | I27: =SUM(I5:I26) -> 1
B29: BALANCE PERSONAL
B30: ACTIVOS Y POSESIONES | F30: PASIVOS
B31: Activos | F31: Deudas
C32: Cuentas bancarias | D32: ='ACTIVOS Y POSESIONES'!B11 -> 3700000 | E32: =D32*100%/$D$52 -> 0.0019719661 | G32: Tarjetas de crédito | H32: =PASIVOS!B10 -> 16500000 | I32: =H32*100%/$H$39 -> 0.032305433
C33: Certificados de deposito | D33: ='ACTIVOS Y POSESIONES'!B16 -> 0 | E33: =D33*100%/$D$52 -> 0 | G33: Hipoteca / Leasing | H33: =PASIVOS!B15 -> 335000000 | I33: =H33*100%/$H$39 -> 0.65589819
C34: Derechos fiduciarios | D34: ='ACTIVOS Y POSESIONES'!B21 -> 44000000 | E34: =D34*100%/$D$52 -> 0.023450408 | G34: Créditos de vehículo | H34: =PASIVOS!B20 -> 65000000 | I34: =H34*100%/$H$39 -> 0.12726383
C35: Bonos soberanos | D35: ='ACTIVOS Y POSESIONES'!B26 -> 0 | E35: =D35*100%/$D$52 -> 0 | G35: Créditos de consumo | H35: =PASIVOS!B25 -> 37750000 | I35: =H35*100%/$H$39 -> 0.073910915
C36: Cuentas AFC/FVP | D36: ='ACTIVOS Y POSESIONES'!B31 -> 10300000 | E36: =D36*100%/$D$52 -> 0.0054895273 | G36: Créditos educativos | H36: =PASIVOS!B30 -> 45000000 | I36: =H36*100%/$H$39 -> 0.088105727
C37: Fondos de inversión | D37: ='ACTIVOS Y POSESIONES'!B38 -> 23000000 | E37: =D37*100%/$D$52 -> 0.012258168 | G37: Créditos personales | H37: =PASIVOS!B35 -> 8500000 | I37: =H37*100%/$H$39 -> 0.016642193
C38: Acciones | D38: ='ACTIVOS Y POSESIONES'!B45 -> 24000000 | E38: =D38*100%/$D$52 -> 0.012791131 | G38: Otros | H38: =PASIVOS!B40 -> 3000000 | I38: =H38*100%/$H$39 -> 0.0058737151
C39: Inmuebles | D39: ='ACTIVOS Y POSESIONES'!B52 -> 605000000 | E39: =D39*100%/$D$52 -> 0.32244311 | F39: Total deudas | H39: =SUM(H32:H38) -> 510750000 | I39: =SUM(I32:I38) -> 1
C40: Negocios | D40: ='ACTIVOS Y POSESIONES'!B59 -> 325000000 | E40: =D40*100%/$D$52 -> 0.17321324
C41: Ganado | D41: ='ACTIVOS Y POSESIONES'!B64 -> 35000000 | E41: =D41*100%/$D$52 -> 0.018653733 | G41: % de deuda/activos Dian | H41: =H39*100%/D52 -> 0.27221127
C42: Otros | D42: ='ACTIVOS Y POSESIONES'!B69 -> 0 | E42: =D42*100%/$D$52 -> 0
B43: Total activos | D43: =SUM(D32:D42) -> 1070000000 | E43: =SUM(E32:E42) -> 0.57027128
B46: Posesiones
C47: Inmuebles | D47: ='ACTIVOS Y POSESIONES'!B76 -> 630000000 | E47: =D47*100%/$D$52 -> 0.3357672
C48: Vehiculos | D48: ='ACTIVOS Y POSESIONES'!B83 -> 146300000 | E48: =D48*100%/$D$52 -> 0.077972606
C49: Otros | D49: ='ACTIVOS Y POSESIONES'!B88 -> 30000000 | E49: =D49*100%/$D$52 -> 0.015988914
B50: Total posesiones | D50: =SUM(D47:D49) -> 806300000 | E50: =SUM(E47:E49) -> 0.42972872
B52: Activos para La DIAN y los bancos | D52: =D43+D50 -> 1876300000 | E52: =E43+E50 -> 1 | F52: Patrimonio Neto para La DIAN y los bancos | H52: =D52-H39 -> 1365550000
B53: Activos para su libertad financiera | D53: =D43 -> 1070000000 | E53: =E43 -> 0.57027128 | F53: Patrimonio Neto para su libertad financiera | H53: =D53-H39 -> 559250000

Sheet GASTOS
B2: GASTOS
B3: ARRIENDO/HIPOTECA | C3: 1700000 | D3: =C3*100%/$G$54 -> 0.43234995 | F3: PROVISIÓN IMPUESTOS | G3: =SUM(G4:G6) -> 0 | H3: =G3*100%/$G$54 -> 0
B4: SERVICIOS PUBLICOS | C4: =SUM(C5:C10) -> 370000 | D4: =C4*100%/$G$54 -> 0.094099695 | F4: Vehículos | G4: 0 | H4: =G4*100%/$G$54 -> 0
B5: Agua | C5: 150000 | D5: =C5*100%/$G$54 -> 0.038148525 | F5: Predial | G5: 0 | H5: =G5*100%/$G$54 -> 0
B6: Luz | C6: 40000 | D6: =C6*100%/$G$54 -> 0.01017294 | F6: Valorización | G6: 0 | H6: =G6*100%/$G$54 -> 0
B7: Teléfono | C7: 140000 | D7: =C7*100%/$G$54 -> 0.03560529 | F7: PROVISIÓN SEGUROS | G7: =SUM(G8:G11) -> 0 | H7: =G7*100%/$G$54 -> 0
B8: Internet | C8: 0 | D8: =C8*100%/$G$54 -> 0 | F8: Soat | G8: 0 | H8: =G8*100%/$G$54 -> 0
B9: Televisión | C9: 0 | D9: =C9*100%/$G$54 -> 0 | F9: Todo riesgo vehículo | G9: 0 | H9: =G9*100%/$G$54 -> 0
B10: Celular | C10: 40000 | D10: =C10*100%/$G$54 -> 0.01017294 | F10: Todo riesgo casa | G10: 0 | H10: =G10*100%/$G$54 -> 0
B11: GASTOS VIVIENDA | C11: =SUM(C12:C15) -> 70000 | D11: =C11*100%/$G$54 -> 0.017802645 | F11: Poliza vida | G11: 0 | H11: =G11*100%/$G$54 -> 0
B12: Administración | C12: 70000 | D12: =C12*100%/$G$54 -> 0.017802645 | F12: DEPORTES/GIMNASIO | G12: 0 | H12: =G12*100%/$G$54 -> 0
B13: Cuotas extraordinarias | C13: 0 | D13: =C13*100%/$G$54 -> 0 | F13: ENTRETENIMIENTO | G13: =SUM(G14:G18) -> 60000 | H13: =G13*100%/$G$54 -> 0.01525941
B14: Mantenimiento | C14: 0 | D14: =C14*100%/$G$54 -> 0 | F14: Cine | G14: 40000 | H14: =G14*100%/$G$54 -> 0.01017294
B15: Multas / Sanciones | C15: 0 | D15: =C15*100%/$G$54 -> 0 | F15: Paseos | G15: 0 | H15: =G15*100%/$G$54 -> 0
B16: MERCADO | C16: 600000 | D16: =C16*100%/$G$54 -> 0.1525941 | F16: Restaurantes | G16: 0 | H16: =G16*100%/$G$54 -> 0
B17: GASTOS VEHÍCULO | C17: =C18 -> 0 | D17: =C17*100%/$G$54 -> 0 | F17: Parques de diversión | G17: 20000 | H17: =G17*100%/$G$54 -> 0.00508647
B18: Mantenimiento | C18: 0 | D18: =C18*100%/$G$54 -> 0 | F18: "Rumba" | G18: 0 | H18: =G18*100%/$G$54 -> 0
B19: GASTOS HIJOS | C19: =SUM(C20:C25) -> 610000 | D19: =C19*100%/$G$54 -> 0.15513733 | F19: SOCIALES | G19: =SUM(G20:G23) -> 50000 | H19: =G19*100%/$G$54 -> 0.012716175
B20: Pensión | C20: 450000 | D20: =C20*100%/$G$54 -> 0.11444557 | F20: Cumpleaños | G20: 50000 | H20: =G20*100%/$G$54 -> 0.012716175
B21: Ruta | C21: 100000 | D21: =C21*100%/$G$54 -> 0.02543235 | F21: Matrimonios | G21: 0 | H21: =G21*100%/$G$54 -> 0
B22: Onces | C22: 60000 | D22: =C22*100%/$G$54 -> 0.01525941 | F22: Bautizos | G22: 0 | H22: =G22*100%/$G$54 -> 0
B23: Mesada | C23: 0 | D23: =C23*100%/$G$54 -> 0 | F23: Otros | G23: 0 | H23: =G23*100%/$G$54 -> 0
B24: Ropa | C24: 0 | D24: =C24*100%/$G$54 -> 0 | F24: MASCOTA | G24: =SUM(G25:G29) -> 0 | H24: =G24*100%/$G$54 -> 0
B25: Otros | C25: 0 | D25: =C25*100%/$G$54 -> 0 | F25: Concentrado | G25: 0 | H25: =G25*100%/$G$54 -> 0
B26: GASTOS CONYUGE | C26: 0 | D26: =C26*100%/$G$54 -> 0 | F26: Entrenador | G26: 0 | H26: =G26*100%/$G$54 -> 0
B27: CREDITOS | C27: =SUM(C28:C40) -> 350000 | D27: =C27*100%/$G$54 -> 0.089013225 | F27: Veterinario | G27: 0 | H27: =G27*100%/$G$54 -> 0
B28: Vehículo | C28: 0 | D28: =C28*100%/$G$54 -> 0 | F28: Baño | G28: 0 | H28: =G28*100%/$G$54 -> 0
B29: Rotativo | C29: 0 | D29: =C29*100%/$G$54 -> 0 | F29: Otros | G29: 0 | H29: =G29*100%/$G$54 -> 0
B30: Libranza | C30: 300000 | D30: =C30*100%/$G$54 -> 0.07629705 | F30: AHORRO E INVERSIÓN | G30: 0 | H30: =G30*100%/$G$54 -> 0
B31: Visa | C31: 0 | D31: =C31*100%/$G$54 -> 0 | F31: SERVICIO DOMESTICO | G31: =SUM(G32:G34) -> 0 | H31: =G31*100%/$G$54 -> 0
B32: Master | C32: 0 | D32: =C32*100%/$G$54 -> 0 | F32: Salario | G32: 0 | H32: =G32*100%/$G$54 -> 0
B33: Diners | C33: 0 | D33: =C33*100%/$G$54 -> 0 | F33: Prestaciones | G33: 0 | H33: =G33*100%/$G$54 -> 0
B34: American Express | C34: 0 | D34: =C34*100%/$G$54 -> 0 | F34: Dotación | G34: 0 | H34: =G34*100%/$G$54 -> 0
B35: Codensa | C35: 50000 | D35: =C35*100%/$G$54 -> 0.012716175 | F35: SALUD | G35: =SUM(G36:G38) -> 0 | H35: =G35*100%/$G$54 -> 0
B36: CMR | C36: 0 | D36: =C36*100%/$G$54 -> 0 | F36: Prepagada | G36: 0 | H36: =G36*100%/$G$54 -> 0
B37: Tarjeta Alkosto | C37: 0 | D37: =C37*100%/$G$54 -> 0 | F37: Vales | G37: 0 | H37: =G37*100%/$G$54 -> 0
B38: Tarjeta Éxito | C38: 0 | D38: =C38*100%/$G$54 -> 0 | F38: Medicamentos | G38: 0 | H38: =G38*100%/$G$54 -> 0
B39: Tarjeta Multiservicios | C39: 0 | D39: =C39*100%/$G$54 -> 0 | F39: GASTOS PERSONALES | G39: =SUM(G40:G48) -> 106000 | H39: =G39*100%/$G$54 -> 0.026958291
B40: Otros | C40: 0 | D40: =C40*100%/$G$54 -> 0 | F40: Alimentación | G40: 0 | H40: =G40*100%/$G$54 -> 0
B41: GASTOS BANCARIOS | C41: =SUM(C42:C54) -> 16000 | D41: =C41*100%/$G$54 -> 0.004069176 | F41: Transporte | G41: 100000 | H41: =G41*100%/$G$54 -> 0.02543235
B42: Cuota de manejo cuenta | C42: 12000 | D42: =C42*100%/$G$54 -> 0.003051882 | F42: Gasolina | G42: 0 | H42: =G42*100%/$G$54 -> 0
B43: Cuota de manejo Visa | C43: 0 | D43: =C43*100%/$G$54 -> 0 | F43: Peajes / Cobros por congestión | G43: 0 | H43: =G43*100%/$G$54 -> 0
B44: Cuota de manejo Master | C44: 0 | D44: =C44*100%/$G$54 -> 0 | F44: Peluqueria | G44: 6000 | H44: =G44*100%/$G$54 -> 0.001525941
B45: Cuota de manejo American | C45: 0 | D45: =C45*100%/$G$54 -> 0 | F45: Lavanderia | G45: 0 | H45: =G45*100%/$G$54 -> 0
B46: Cuota de manejo Diners | C46: 0 | D46: =C46*100%/$G$54 -> 0 | F46: Parqueaderos | G46: 0 | H46: =G46*100%/$G$54 -> 0
B47: Cuota de manejo Codensa | C47: 4000 | D47: =C47*100%/$G$54 -> 0.001017294 | F47: Vestido | G47: 0 | H47: =G47*100%/$G$54 -> 0
B48: Cuota de manejo CMR | C48: 0 | D48: =C48*100%/$G$54 -> 0 | F48: Varios | G48: 0 | H48: =G48*100%/$G$54 -> 0
B49: Cuota de manejo Alkosto | C49: 0 | D49: =C49*100%/$G$54 -> 0 | F49: DONACIONES | G49: 0 | H49: =G49*100%/$G$54 -> 0
B50: Cuota de manejo Éxito | C50: 0 | D50: =C50*100%/$G$54 -> 0 | F50: IMPREVISTOS | G50: 50000 | H50: =G50*100%/$G$54 -> 0.012716175
B51: Cuota de manejo Multiservicios | C51: 0 | D51: =C51*100%/$G$54 -> 0 | F51: OTROS | G51: 0 | H51: =G51*100%/$G$54 -> 0
B52: 4 x 1000 | C52: 0 | D52: =C52*100%/$G$54 -> 0
B53: Retiros | C53: 0 | D53: =C53*100%/$G$54 -> 0
B54: Consultas | C54: 0 | D54: =C54*100%/$G$54 -> 0 | F54: TOTAL GASTOS | G54: =C3+C4+C11+C16+C17+C19+C26+C27+C41+G3+G7+G12+G13+G24+G30+G31+G35+G39+G49+G50+G51 -> 3932000 | H54: =D3+D4+D11+D16+D17+D19+D26+D27+D41+H3+H7+H12+H13+H24+H30+H31+H35+H39+H49+H50+H51 -> 1

Sheet ACTIVOS Y POSESIONES
A2: ACTIVOS Y POSESIONES
A3: Detalle | B3: Valor | C3: Observaciones
A4: ACTIVOS
A5: Cuentas bancarias
A6: Citibank cuenta corriente | B6: 0 | C6: Helm Bank | D6: =B6*100%/$B$90 -> 0
A7: Citibank cuenta ahorros | B7: 700000 | D7: =B7*100%/$B$90 -> 0.00037307467
A8: Helm cuenta corriente | B8: 0 | D8: =B8*100%/$B$90 -> 0
A9: Helm cuenta ahorros | B9: 3000000 | D9: =B9*100%/$B$90 -> 0.0015988914
B10: 0 | D10: =B10*100%/$B$90 -> 0
A11: Total cuentas bancarias | B11: =SUM(B6:B10) -> 3700000 | D11: =B11*100%/$B$90 -> 0.0019719661
A12: Certificados de deposito
A13: CDT Helm | B13: 0 | D13: =B13*100%/$B$90 -> 0
B14: 0 | D14: =B14*100%/$B$90 -> 0
B15: 0 | D15: =B15*100%/$B$90 -> 0
A16: Total certificados de deposito | B16: =SUM(B13:B15) -> 0 | D16: =B16*100%/$B$90 -> 0
A17: Derechos Fiduciarios
A18: Helm fiduciaria | B18: 0 | D18: =B18*100%/$B$90 -> 0
A19: BD Bacata | B19: 44000000 | D19: =B19*100%/$B$90 -> 0.023450408
A20: Oikos | B20: 0 | C20: Hotel Pop Art | D20: =B20*100%/$B$90 -> 0
A21: Total derechos fiduciarios | B21: =SUM(B18:B20) -> 44000000 | D21: =B21*100%/$B$90 -> 0.023450408
A22: Bonos soberanos
A23: TES 2018 | D23: =B23*100%/$B$90 -> 0
A24: Bonos reserva federal USA 2020 | B24: 0 | D24: =B24*100%/$B$90 -> 0
B25: 0 | D25: =B25*100%/$B$90 -> 0
A26: Total bonos soberanos | B26: =SUM(B23:B25) -> 0 | D26: =B26*100%/$B$90 -> 0
A27: Cuentas AFC/FVP
A28: Helm Bank AFC | B28: 0 | D28: =B28*100%/$B$90 -> 0
A29: Dafuturo | B29: 10000000 | C29: FVP | D29: =B29*100%/$B$90 -> 0.0053296381
A30: Davivienda AFC | B30: 300000 | D30: =B30*100%/$B$90 -> 0.00015988914
A31: Total cuentas AFC/FVP | B31: =SUM(B28:B30) -> 10300000 | D31: =B31*100%/$B$90 -> 0.0054895273
A32: Fondos de Inversión
A33: Corredores | B33: 7000000 | C33: Fondo interes | D33: =B33*100%/$B$90 -> 0.0037307467
A34: Corredores | B34: 15000000 | C34: Multiescala 60 | D34: =B34*100%/$B$90 -> 0.0079944572
A35: Corredores | B35: 1000000 | C35: Fondo acción | D35: =B35*100%/$B$90 -> 0.00053296381
A36: Valores Bancolombia | B36: 0 | D36: =B36*100%/$B$90 -> 0
B37: 0 | D37: =B37*100%/$B$90 -> 0
A38: Total fondos de Inversión | B38: =SUM(B33:B37) -> 23000000 | D38: =B38*100%/$B$90 -> 0.012258168
A39: Acciones
A40: Corficolombiana | B40: 15300000 | C40: 397 acciones | D40: =B40*100%/$B$90 -> 0.0081543463
A41: Ecopetrol | B41: 8700000 | C41: 6,215 acciones | D41: =B41*100%/$B$90 -> 0.0046367852
B42: 0 | D42: =B42*100%/$B$90 -> 0
B43: 0 | D43: =B43*100%/$B$90 -> 0
B44: 0 | D44: =B44*100%/$B$90 -> 0
A45: Total acciones | B45: =SUM(B40:B44) -> 24000000 | D45: =B45*100%/$B$90 -> 0.012791131
A46: Inmuebles
A47: KR 6 129A-36 AP 1503 | B47: 525000000 | C47: Inmueble que genera renta | D47: =B47*100%/$B$90 -> 0.279806
A48: C.C. San Ambrosio local 2-31 | B48: 80000000 | C48: Local que genera renta | D48: =B48*100%/$B$90 -> 0.042637105
B49: 0 | D49: =B49*100%/$B$90 -> 0
B50: 0 | D50: =B50*100%/$B$90 -> 0
B51: 0 | D51: =B51*100%/$B$90 -> 0
A52: Total inmuebles | B52: =SUM(B47:B51) -> 605000000 | D52: =B52*100%/$B$90 -> 0.32244311
A53: Negocios
A54: Deli Burguer | B54: 25000000 | D54: =B54*100%/$B$90 -> 0.013324095
A55: Inversiones Phoenix | B55: 300000000 | D55: =B55*100%/$B$90 -> 0.15988914
B56: 0 | D56: =B56*100%/$B$90 -> 0
B57: 0 | D57: =B57*100%/$B$90 -> 0
B58: 0 | D58: =B58*100%/$B$90 -> 0
A59: Total negocios | B59: =SUM(B54:B58) -> 325000000 | D59: =B59*100%/$B$90 -> 0.17321324
A60: Ganado
A61: Vacas Holstein | B61: 20000000 | C61: ganado lechero | D61: =B61*100%/$B$90 -> 0.010659276
A62: Novillos Simbrah | B62: 15000000 | C62: ganado de carne | D62: =B62*100%/$B$90 -> 0.0079944572
B63: 0 | D63: =B63*100%/$B$90 -> 0
A64: Total ganado | B64: =SUM(B61:B63) -> 35000000 | D64: =B64*100%/$B$90 -> 0.018653733
A65: Otros
B66: 0 | D66: =B66*100%/$B$90 -> 0
B67: 0 | D67: =B67*100%/$B$90 -> 0
B68: 0 | D68: =B68*100%/$B$90 -> 0
A69: Total otros | B69: =SUM(B66:B68) -> 0 | D69: =B69*100%/$B$90 -> 0
A70: TOTAL ACTIVOS | B70: =+B11+B16+B21+B26+B31+B38+B45+B52+B59+B64+B69 -> 1070000000 | C70: =+C11+C16+C21+C26+C31+C38+C45+C52+C59+C64+C69 -> 0 | D70: =+D11+D16+D21+D26+D31+D38+D45+D52+D59+D64+D69 -> 0.57027128
A71: POSESIONES
A72: Inmuebles
A73: KR 26 67-13 IN3 AP 605 | B73: 415000000 | C73: Vivienda de habitación | D73: =B73*100%/$B$90 -> 0.22117998
A74: Casa Anapoima | B74: 215000000 | C74: Casa de descanso | D74: =B74*100%/$B$90 -> 0.11458722
B75: 0 | D75: =B75*100%/$B$90 -> 0
A76: Total inmuebles | B76: =SUM(B73:B75) -> 630000000 | D76: =B76*100%/$B$90 -> 0.3357672
A77: Vehículos
A78: Chevrolet Spark DCH 305 | B78: 17000000 | D78: =B78*100%/$B$90 -> 0.0090603848
A79: BMW 325 HBU426 | B79: 125000000 | D79: =B79*100%/$B$90 -> 0.066620476
A80: AKT 125 | B80: 4300000 | D80: =B80*100%/$B$90 -> 0.0022917444
B81: 0 | D81: =B81*100%/$B$90 -> 0
B82: 0 | D82: =B82*100%/$B$90 -> 0
A83: Total vehículos | B83: =SUM(B77:B82) -> 146300000 | D83: =B83*100%/$B$90 -> 0.077972606
A84: Otros
A85: Gordas chismosas | B85: 15000000 | C85: Obra de Fernando Botero | D85: =B85*100%/$B$90 -> 0.0079944572
A86: Conejos en celo | B86: 15000000 | C86: Escultura de Sara Acuña | D86: =B86*100%/$B$90 -> 0.0079944572
B87: 0 | D87: =B87*100%/$B$90 -> 0
A88: Total otros | B88: =SUM(B84:B87) -> 30000000 | D88: =B88*100%/$B$90 -> 0.015988914
A89: TOTAL POSESIONES | B89: =SUM(B76+B83+B88) -> 806300000 | C89: =SUM(C76+C83+C88) -> 0 | D89: =SUM(D76+D83+D88) -> 0.42972872
A90: TOTAL ACTIVOS Y POSESIONES | B90: =B70+B89 -> 1876300000 | C90: =C70+C89 -> 0 | D90: =D70+D89 -> 1

Sheet PASIVOS
A1: PASIVOS
A2: Detalle | B2: Valor | C2: Observaciones
A4: Tarjetas de crèdito
A5: Visa Gold | B5: 500000 | C5: Helm Bank | D5: =B5*100%/$B$41 -> 0.00097895252
A6: Diners | B6: 1000000 | C6: Davivienda | D6: =B6*100%/$B$41 -> 0.001957905
A7: CMR | B7: 12000000 | C7: Falabella | D7: =B7*100%/$B$41 -> 0.02349486
B8: 3000000 | D8: =B8*100%/$B$41 -> 0.0058737151
B9: 0 | D9: =B9*100%/$B$41 -> 0
A10: Total tarjetas de credito | B10: =SUM(B5:B9) -> 16500000 | D10: =B10*100%/$B$41 -> 0.032305433
A11: Hipoteca / Leasing
A12: KR 26 67-13 IN3 AP 605 | B12: 200000000 | C12: Vivienda de habitación | D12: =B12*100%/$B$41 -> 0.39158101
A13: Casa Anapoima | B13: 135000000 | C13: Casa de descanso | D13: =B13*100%/$B$41 -> 0.26431718
B14: 0 | D14: =B14*100%/$B$41 -> 0
A15: Total hipoteca / leasing | B15: =SUM(B12:B14) -> 335000000 | D15: =B15*100%/$B$41 -> 0.65589819
A16: Creditos de vehìculo
A17: BMW 325 HBU426 | B17: 65000000 | C17: Vivienda de habitación | D17: =B17*100%/$B$41 -> 0.12726383
C18: Casa de descanso | D18: =B18*100%/$B$41 -> 0
B19: 0 | D19: =B19*100%/$B$41 -> 0
A20: Total creditos de vehiculo | B20: =SUM(B17:B19) -> 65000000 | D20: =B20*100%/$B$41 -> 0.12726383
A21: Creditos de consumo
A22: Credicash | B22: 35000000 | C22: Helm Bank | D22: =B22*100%/$B$41 -> 0.068526676
A23: Daviexpress | B23: 2000000 | C23: Davivienda | D23: =B23*100%/$B$41 -> 0.0039158101
B24: 750000 | C24: Fondo empleados | D24: =B24*100%/$B$41 -> 0.0014684288
A25: Total creditos de consumo | B25: =SUM(B22:B24) -> 37750000 | D25: =B25*100%/$B$41 -> 0.073910915
A26: Creditos educativos
A27: MBA | B27: 45000000 | C27: Icetex | D27: =B27*100%/$B$41 -> 0.088105727
D28: =B28*100%/$B$41 -> 0
B29: 0 | D29: =B29*100%/$B$41 -> 0
A30: Total creditos educativos | B30: =SUM(B27:B29) -> 45000000 | D30: =B30*100%/$B$41 -> 0.088105727
A31: Creditos personales
B32: 6500000 | C32: Deudas familiares | D32: =B32*100%/$B$41 -> 0.012726383
B33: 2000000 | C33: Cadena amigos | D33: =B33*100%/$B$41 -> 0.0039158101
B34: 0 | D34: =B34*100%/$B$41 -> 0
A35: Total creditos personalees | B35: =SUM(B32:B34) -> 8500000 | D35: =B35*100%/$B$41 -> 0.016642193
A36: Otros crèditos
B37: 1000000 | C37: Amway | D37: =B37*100%/$B$41 -> 0.001957905
B38: 2000000 | C38: Zrii | D38: =B38*100%/$B$41 -> 0.0039158101
B39: 0 | D39: =B39*100%/$B$41 -> 0
A40: Total otros creditos | B40: =SUM(B37:B39) -> 3000000 | D40: =B40*100%/$B$41 -> 0.0058737151
A41: TOTAL PASIVOS | B41: =B10+B15+B20+B25+B30+B35+B40 -> 510750000 | D41: =D10+D15+D20+D25+D30+D35+D40 -> 1
