Workbook

Sheet Resumen
A1: Casa La Clarita — Rendición de cuentas e inversión
A2: Preparado por Felipe Fajardo para Jorge Quintero · corte 30 de septiembre de 2026 · cifras en pesos colombianos
A4: 1. ¿Cuánto se ha invertido?
A5: Contratista principal (contrato $85M + adicionales $29M) | B5: =SUMIFS(Movimientos!$I$6:$I$205,Movimientos!$C$6:$C$205,"Obra – contratista principal",Movimientos!$L$6:$L$205,"Gasto") -> 114000000
A6: Adecuación eléctrica y aumento de carga (incluye saldo pendiente) | B6: =SUMIFS(Movimientos!$I$6:$I$205,Movimientos!$C$6:$C$205,"Eléctrico – aumento de carga (Enel)",Movimientos!$L$6:$L$205,"Gasto") -> 5000000
A7: Cámaras de seguridad | B7: =SUMIFS(Movimientos!$I$6:$I$205,Movimientos!$C$6:$C$205,"Seguridad – cámaras",Movimientos!$L$6:$L$205,"Gasto") -> 4999785
A8: Bomba de presión (equipo + instalación) | B8: =SUMIFS(Movimientos!$I$6:$I$205,Movimientos!$C$6:$C$205,"Hidráulico – bomba de presión",Movimientos!$L$6:$L$205,"Gasto") -> 610000
A9: Impuesto 4x1000 de transferencias | B9: =SUMIFS(Movimientos!$I$6:$I$205,Movimientos!$C$6:$C$205,"Costos bancarios – 4x1000",Movimientos!$L$6:$L$205,"Gasto") -> 96188
A10: Mobiliario habitación 1 | B10: =SUMIFS(Movimientos!$I$6:$I$205,Movimientos!$C$6:$C$205,"Mobiliario – habitaciones",Movimientos!$L$6:$L$205,"Gasto") -> 6551800
A11: TOTAL INVERTIDO Y COMPROMETIDO | B11: =Movimientos!$I$4 -> 131257773
A12: Ya pagado | B12: =Cuadre!$B$31 -> 129707773
A13: Pendiente de pago | B13: =Cuadre!$B$32 -> 1550000
A15: 2. ¿De dónde salió el dinero?
A16: Abuelos – capital propio | B16: =SUMIFS(Movimientos!$I$6:$I$205,Movimientos!$F$6:$F$205,"Abuelos – capital propio",Movimientos!$L$6:$L$205,"Gasto") -> 89880000
A17: Préstamo mamá | B17: =SUMIFS(Movimientos!$I$6:$I$205,Movimientos!$F$6:$F$205,"Préstamo mamá",Movimientos!$L$6:$L$205,"Gasto") -> 34515973
A18: TC abuelos (cuotas) | B18: =SUMIFS(Movimientos!$I$6:$I$205,Movimientos!$F$6:$F$205,"TC abuelos (cuotas)",Movimientos!$L$6:$L$205,"Gasto") -> 6861800
A19: Sobrante del préstamo en la cuenta de la abuela | B19: =Cuadre!$B$20 -> 500215
A21: 3. Lo que falta por invertir (proyectado)
A22: Mobiliario habitaciones 2 a 7 (estimado) | B22: =Supuestos!$I$13-Mobiliario!$B$44 -> 39310800
A23: Lavandería (lavadora + monedero) | B23: =Supuestos!$B$45 -> 4020000
A24: Menos: venta de objetos almacenados | B24: =-Supuestos!$F$28 -> 0
A25: Intereses del préstamo de mamá (36 cuotas) | B25: =Préstamo!$B$13 -> 12632761
A26: INVERSIÓN TOTAL A RECUPERAR | B26: =Escenarios!$B$10 -> 1.8722133e+08
A28: 4. ¿Qué va a producir la casa? (casa completa: 7 habitaciones + lavandería)
A29: Ingreso bruto mensual (arriendos + lavandería) | B29: =Escenarios!$B$16 -> 9246000
A30: Gastos de operación | B30: =Escenarios!$B$17 -> -3418466.7
A31: Comisión de administración | B31: =INDEX(Escenarios!$B$19:$D$19,MATCH(Supuestos!$B$28,Escenarios!$B$15:$D$15,0)) -> -1165506.7
A32: Comisión seleccionada (sobre ingreso neto) | B32: =Supuestos!$B$28 -> 0.2
A33: GANANCIA MENSUAL PARA LOS ABUELOS | B33: =INDEX(Escenarios!$B$20:$D$20,MATCH(Supuestos!$B$28,Escenarios!$B$15:$D$15,0)) -> 4662026.7
A34: Cuota préstamo de mamá (dic 2026 – nov 2029) | B34: =Escenarios!$B$21 -> -1323132.2
A35: Ganancia mensual mientras se paga el préstamo | B35: =INDEX(Escenarios!$B$22:$D$22,MATCH(Supuestos!$B$28,Escenarios!$B$15:$D$15,0)) -> 3338894.4
A36: Mientras la hab. 7 sea bodega (6 hab.), mientras se paga el préstamo | B36: =INDEX(Escenarios!$B$50:$D$50,MATCH(Supuestos!$B$28,Escenarios!$B$15:$D$15,0)) -> 2535267.8
A37: Antes de la remodelación | B37: =Supuestos!$B$50 -> 620000
A39: 5. ¿En cuánto tiempo se recupera?
A40: Meses para recuperar toda la inversión (desde oct 2026) | B40: =INDEX(Escenarios!$B$26:$D$26,MATCH(Supuestos!$B$28,Escenarios!$B$15:$D$15,0)) -> 45
A41: Mes estimado de recuperación total | B41: =INDEX(Escenarios!$B$27:$D$27,MATCH(Supuestos!$B$28,Escenarios!$B$15:$D$15,0)) -> 47635
A42: Rentabilidad anual de la casa | B42: =INDEX(Escenarios!$B$24:$D$24,MATCH(Supuestos!$B$28,Escenarios!$B$15:$D$15,0)) -> 0.29881381
A43: vs. CDT a 1 año (promedio del mercado) | B43: =Supuestos!$B$40 -> 0.1207
A44: vs. cuenta de ahorros actual | B44: =Supuestos!$B$38 -> 0.085
A46: 6. ¿Cuánto podría valer la casa? (referencia, no avalúo)
A47: Rango bajo | B47: =Valoración!$B$41 -> 6.0292814e+08
A48: Rango alto | B48: =Valoración!$B$42 -> 8.1038731e+08
A50: Detalle de cada pago en la hoja Movimientos. Supuestos editables en la hoja Supuestos. Celdas amarillas = por confirmar.

Sheet Propuesta
A1: Propuesta: separar la inversión del flujo mensual de la casa
A2: Preparado por Felipe Fajardo para Jorge Quintero · corte 30 de septiembre de 2026
A4: 1. Lo que pasó en septiembre
A5: Arriendo cobrado Habitación 1 | D5: ='Registro Mensual'!$C$6 -> 1250000
A6: Primera cuota de la tarjeta (muebles de la Habitación 1) | D6: =-'Registro Mensual'!$K$6 -> -1190248
A7: Servicios del mes | D7: =-'Registro Mensual'!$D$6 -> -606000
A8: Resultado del mes | D8: ='Registro Mensual'!$C$6-'Registro Mensual'!$K$6-'Registro Mensual'!$D$6 -> -546248
A9: Después de pagar la primera cuota de los muebles y los servicios, el mes cerró en negativo. Desde el segundo mes cada habitación amoblada suma una cuota de ~$850.000. Si cada habitación nueva se amuebla a cuotas y se paga con el arriendo, y desde diciembre además se paga el préstamo de mamá con el mismo arriendo, la casa no alcanza a cubrir sus obligaciones durante el primer año y no deja ganancia para nadie.
A13: 2. El principio: dos cajas separadas
A14: Caja de INVERSIÓN (se paga una sola vez): remodelación, muebles, lavadora. La obra se pagó con ahorros y con el préstamo, no con el arriendo. Los muebles son parte de esa misma inversión.
A16: Caja de OPERACIÓN (cada mes): arriendos menos servicios, reservas y administración. De aquí sale la cuota del préstamo de mamá, y lo que sobra es la ganancia real de la casa.
A19: 3. Si el arriendo paga también los muebles (Opción A)
A20: Cuota mensual del préstamo de mamá desde el 15 dic 2026 | D20: =Préstamo!$B$11 -> 1323132.2
A21: Meses con caja negativa en los primeros 12 meses | D21: =Comparación!$B$26 -> 9
A22: Peor momento acumulado de la caja de la casa | D22: =Comparación!$B$27 -> -19254194
A23: Ese faltante tendría que salir de algún lado. Si no sale de los ahorros, se atrasa la cuota a mamá o la de la tarjeta. Es decir, la plata de los muebles termina saliendo de los ahorros de todas formas, pero tarde y en desorden.
A27: 4. Lo que propongo (Opción B)
A28: a) Pagar las cuotas de los muebles y de la lavandería desde la cuenta de ahorros, no desde el arriendo. Se siguen aprovechando las cuotas sin interés de Mercado Libre: no hay que pagar de contado, solo cambiar de qué cuenta sale cada cuota.
A31: b) El arriendo paga la operación de la casa y la cuota del préstamo de mamá. Desde que se arriendan las 6 habitaciones alcanza para todo y sobra; con la 7 sobra más.
A33: Ganancia mensual mientras se paga el préstamo — 6 habitaciones | D33: =INDEX(Escenarios!$B$50:$D$50,MATCH(Supuestos!$B$28,Escenarios!$B$15:$D$15,0)) -> 2535267.8
A34: Ganancia mensual mientras se paga el préstamo — casa completa (7) | D34: =INDEX(Escenarios!$B$22:$D$22,MATCH(Supuestos!$B$28,Escenarios!$B$15:$D$15,0)) -> 3338894.4
A35: Ganancia mensual cuando termine el préstamo — casa completa (7) | D35: =INDEX(Escenarios!$B$20:$D$20,MATCH(Supuestos!$B$28,Escenarios!$B$15:$D$15,0)) -> 4662026.7
A36: c) Cambiar la lavadora de más de 20 años por una nueva e instalar un monedero para cobrar por ciclo. El monedero ordena el uso de la máquina entre 7 inquilinos y convierte la lavandería en un ingreso. El contrato de arriendo ya contempla el cobro por ciclo; hoy el uso es gratis hasta que se instale. El monedero se compra a cuotas sin interés.
A39: Lavadora nueva | D39: =Mobiliario!$C$52 -> 2830000
A40: Monedero | D40: =Mobiliario!$B$54*Mobiliario!$B$56 -> 1190000
A41: Ingreso mensual estimado del monedero (casa completa) | D41: =Supuestos!$F$30*Supuestos!$F$29*Supuestos!$F$32*COUNTA(Supuestos!$A$6:$A$12) -> 196000
A42: Ahorro mensual en energía y agua (lavadora nueva) | D42: =Supuestos!$B$47 -> 45000
A43: Meses para que la lavandería completa se pague sola | D43: =IFERROR(Supuestos!$B$45/(D41+D42),0) -> 16.680498
A44: d) El dinero que se quiera guardar para otra propiedad rinde más en un CDT a 1 año (~12% EA promedio del mercado) que en la cuenta actual (8,5%).
A46: Rendimiento extra al año por cada $10.000.000 | D46: =Comparación!$B$33 -> 357000
A47: e) Habilitar la habitación 7 cuando salgan los objetos almacenados (se trasladan a la nueva propiedad o se venden). Si se venden, lo recibido ayuda a pagar el mobiliario de esa habitación. Los objetos probablemente valen menos de $10.000.000, y cada mes de bodega deja de producir la ganancia de abajo: en un año, mantener la bodega cuesta aproximadamente lo mismo que valen los objetos.
A50: Canon esperado habitación 7 | D50: =Supuestos!$C$12 -> 1400000
A51: Fecha estimada | D51: =Supuestos!$D$12 -> 46844
A52: Mobiliario habitación 7 (estimado) | D52: =Mobiliario!$H$44 -> 6551800
A53: Ganancia mensual adicional para los abuelos con la habitación 7 | D53: =INDEX(Escenarios!$B$20:$D$20,MATCH(Supuestos!$B$28,Escenarios!$B$15:$D$15,0))-INDEX(Escenarios!$B$48:$D$48,MATCH(Supuestos!$B$28,Escenarios!$B$15:$D$15,0)) -> 803626.67
A54: Lo que deja de producir la bodega en 12 meses | D54: =12*(INDEX(Escenarios!$B$20:$D$20,MATCH(Supuestos!$B$28,Escenarios!$B$15:$D$15,0))-INDEX(Escenarios!$B$48:$D$48,MATCH(Supuestos!$B$28,Escenarios!$B$15:$D$15,0))) -> 9643520
A56: 5. Qué cambia y qué no
A57: Dinero neto que saldría de los ahorros para muebles y lavandería | D57: ='Flujo Proyectado'!$Q$77 -> 49063625
A58: Caja de la casa a 12 meses — Opción A | D58: =Comparación!$C$18 -> -16562241
A59: Caja de la casa a 12 meses — Opción B | D59: =Comparación!$C$19 -> 25949584
A60: La rentabilidad total de la inversión es la misma en las dos opciones. Lo que cambia es que con la Opción B la casa cumple sus obligaciones cada mes, la cuota a mamá está asegurada desde el primer pago y la ganancia real de la casa se ve desde el primer mes.
A64: 6. Decisión pendiente: comisión de administración
A65: Felipe administra las 7 habitaciones: contratos, cobros, servicios, mantenimiento, rotación de inquilinos y marketing. Se presentan tres opciones sobre el ingreso neto (después de gastos). La decisión es de los abuelos. Ver hoja Escenarios.

Sheet Movimientos
A1: Movimientos — cada pago, uno por uno
A2: Documento vivo: agregue una fila por cada pago, recibo firmado o transferencia. Las filas 'Por desglosar' se reemplazan por sus pagos individuales cuando se digitalicen los soportes.
A3: Cómo llenar: escriba en azul · Categoría, Fuente y Estado tienen lista desplegable · Grupo se calcula solo · Tipo: 'Gasto' o 'Traslado'.
H4: Total gastos registrados: | I4: =SUMIFS(I6:I205,L6:L205,"Gasto") -> 131257773
A5: N° | B5: Fecha | C5: Categoría | D5: Concepto / detalle | E5: Proveedor o beneficiario | F5: Fuente del dinero | G5: Quién pagó (cuenta / persona) | H5: Medio | I5: Monto | J5: Soporte (tipo y referencia) | K5: Estado | L5: Tipo | M5: Grupo | N5: Notas
A6: 1 | B6: 46157 | C6: Obra – contratista principal | D6: Anticipo de obra (transferencia 1 de 2) | E6: Germán Segura Rojas (CC 80.127.526) | F6: Abuelos – capital propio | G6: Jorge Enrique Quintero Ruiz — Nu ••8689 | H6: Transferencia | I6: 10000000 | J6: Comprobante Nu 22848468…923405 | K6: Soportado | L6: Gasto | M6: =IF(C6="","",IFERROR(VLOOKUP(C6,Supuestos!$A$58:$B$65,2,FALSE()),"Revisar")) -> Obra y adecuaciones
A7: 2 | B7: 46157 | C7: Obra – contratista principal | D7: Anticipo de obra (transferencia 2 de 2) | E7: Germán Segura Rojas (CC 80.127.526) | F7: Abuelos – capital propio | G7: Jorge Enrique Quintero Ruiz — Nu ••8689 | H7: Transferencia | I7: 10000000 | J7: Comprobante Nu 10341941…199155 | K7: Soportado | L7: Gasto | M7: =IF(C7="","",IFERROR(VLOOKUP(C7,Supuestos!$A$58:$B$65,2,FALSE()),"Revisar")) -> Obra y adecuaciones
A8: 3 | B8: 46157 | C8: Costos bancarios – 4x1000 | D8: Impuesto 4x1000 de las dos transferencias del anticipo | E8: DIAN (vía Nu) | F8: Abuelos – capital propio | G8: Jorge Enrique Quintero Ruiz — Nu ••8689 | H8: Débito automático | I8: 80000 | J8: Mismos comprobantes Nu | K8: Soportado | L8: Gasto | M8: =IF(C8="","",IFERROR(VLOOKUP(C8,Supuestos!$A$58:$B$65,2,FALSE()),"Revisar")) -> Obra y adecuaciones | N8: $40.000 por cada transferencia
A9: 4 | B9: 46167 | C9: Obra – contratista principal | D9: Adelanto obra La Clarita | E9: Germán Segura Rojas (CC 80.127.526) | F9: Abuelos – capital propio | G9: Efectivo retirado por el abuelo, entregado por Felipe | H9: Efectivo | I9: 14000000 | J9: Recibo firmado 25/05/2026 | K9: Soportado | L9: Gasto | M9: =IF(C9="","",IFERROR(VLOOKUP(C9,Supuestos!$A$58:$B$65,2,FALSE()),"Revisar")) -> Obra y adecuaciones
A10: 5 | B10: 46195 | C10: Obra – contratista principal | D10: Avance de obra La Clarita | E10: Germán Segura Rojas (CC 80.127.526) | F10: Abuelos – capital propio | G10: Efectivo retirado por el abuelo, entregado por Felipe | H10: Efectivo | I10: 15000000 | J10: Recibo firmado 22/06/2026 | K10: Soportado | L10: Gasto | M10: =IF(C10="","",IFERROR(VLOOKUP(C10,Supuestos!$A$58:$B$65,2,FALSE()),"Revisar")) -> Obra y adecuaciones
A11: 6 | B11: 46195 | C11: Eléctrico – aumento de carga (Enel) | D11: 50% adecuación eléctrica | E11: Clemente Gregorio Carriazo | F11: Abuelos – capital propio | G11: Efectivo retirado por el abuelo, entregado por Felipe | H11: Efectivo | I11: 2500000 | J11: Recibo firmado 22/06/2026 | K11: Soportado | L11: Gasto | M11: =IF(C11="","",IFERROR(VLOOKUP(C11,Supuestos!$A$58:$B$65,2,FALSE()),"Revisar")) -> Obra y adecuaciones
A12: 7 | B12: 46197 | C12: Obra – contratista principal | D12: Avance obra La Clarita | E12: Germán Segura Rojas (CC 80.127.526) | F12: Abuelos – capital propio | G12: Efectivo retirado por el abuelo, entregado por Felipe | H12: Efectivo | I12: 10500000 | J12: Recibo firmado 24/06/2026 | K12: Soportado | L12: Gasto | M12: =IF(C12="","",IFERROR(VLOOKUP(C12,Supuestos!$A$58:$B$65,2,FALSE()),"Revisar")) -> Obra y adecuaciones
A13: 8 | B13: 46218 | C13: Obra – contratista principal | D13: Pago de obra (adicionales) | E13: Germán Segura Rojas (CC 80.127.526) | F13: Préstamo mamá | G13: Janneth Quintero Ávila — Nu | H13: Transferencia | I13: 10000000 | J13: Comprobante Nu 21299625…062555 | K13: Soportado | L13: Gasto | M13: =IF(C13="","",IFERROR(VLOOKUP(C13,Supuestos!$A$58:$B$65,2,FALSE()),"Revisar")) -> Obra y adecuaciones
A14: 9 | B14: 46218 | C14: Obra – contratista principal | D14: Pago de obra (adicionales) | E14: Germán Segura Rojas (CC 80.127.526) | F14: Préstamo mamá | G14: Janneth Quintero Ávila — Nu | H14: Transferencia | I14: 8000000 | J14: Comprobante Nu 28378064…566602 | K14: Soportado | L14: Gasto | M14: =IF(C14="","",IFERROR(VLOOKUP(C14,Supuestos!$A$58:$B$65,2,FALSE()),"Revisar")) -> Obra y adecuaciones
A15: 10 | B15: 46228 | C15: Eléctrico – aumento de carga (Enel) | D15: Segundo pago adecuación eléctrica | E15: Clemente Gregorio Carriazo | F15: Abuelos – capital propio | G15: Andrés Felipe Fajardo — Nu ••6045 (dinero del abuelo) | H15: Transferencia | I15: 1250000 | J15: Comprobante Nu 13857091…720148 | K15: Soportado | L15: Gasto | M15: =IF(C15="","",IFERROR(VLOOKUP(C15,Supuestos!$A$58:$B$65,2,FALSE()),"Revisar")) -> Obra y adecuaciones
A16: 11 | B16: 46247 | C16: Obra – contratista principal | D16: Pago de obra (adicionales) | E16: Germán Segura Rojas (CC 80.127.526) | F16: Préstamo mamá | G16: Janneth Quintero Ávila — Nu | H16: Transferencia | I16: 10500000 | J16: Comprobante Nu 58860168…806189 | K16: Soportado | L16: Gasto | M16: =IF(C16="","",IFERROR(VLOOKUP(C16,Supuestos!$A$58:$B$65,2,FALSE()),"Revisar")) -> Obra y adecuaciones
A17: 12 | B17: 46218 | C17: Costos bancarios – 4x1000 | D17: Impuesto 4x1000 de las transferencias del 15 jul y 13 ago | E17: DIAN (vía Nu) | F17: Préstamo mamá | G17: Janneth Quintero Ávila — Nu | H17: Débito automático | I17: 16188 | J17: Mismos comprobantes Nu | K17: Soportado | L17: Gasto | M17: =IF(C17="","",IFERROR(VLOOKUP(C17,Supuestos!$A$58:$B$65,2,FALSE()),"Revisar")) -> Obra y adecuaciones | N17: $4.211 + $11.977. Asumido por la cuenta de mamá, adicional a los $35M
A18: 13 | B18: 46272 | C18: Obra – contratista principal | D18: Abono de obra | E18: Germán Segura Rojas (CC 80.127.526) | F18: Abuelos – capital propio | G18: Jorge Enrique Quintero — Davivienda ahorros ••5040 | H18: Transferencia | I18: 15000000 | J18: Davivienda, aprobación 10420591 | K18: Soportado | L18: Gasto | M18: =IF(C18="","",IFERROR(VLOOKUP(C18,Supuestos!$A$58:$B$65,2,FALSE()),"Revisar")) -> Obra y adecuaciones | N18: Destino: cuenta AV Villas ••3613 de Germán Segura
A19: 14 | B19: 46272 | C19: Obra – contratista principal | D19: Abono 1er contrato | E19: Germán Segura Rojas (CC 80.127.526) | F19: Abuelos – capital propio | G19: Efectivo retirado por el abuelo, entregado por Felipe | H19: Efectivo | I19: 5000000 | J19: Recibo firmado 07/09/2026 | K19: Soportado | L19: Gasto | M19: =IF(C19="","",IFERROR(VLOOKUP(C19,Supuestos!$A$58:$B$65,2,FALSE()),"Revisar")) -> Obra y adecuaciones
A20: 15 | B20: 46274 | C20: Seguridad – cámaras | D20: Cámaras — pago 1 | E20: Oscar Mauricio Herrera Bello | F20: Préstamo mamá | G20: Janneth Quintero Ávila — Nu ••0510 | H20: Transferencia | I20: 2221135 | J20: Comprobante Nu 10234145…242438 | K20: Soportado | L20: Gasto | M20: =IF(C20="","",IFERROR(VLOOKUP(C20,Supuestos!$A$58:$B$65,2,FALSE()),"Revisar")) -> Obra y adecuaciones
A21: 16 | B21: 46280 | C21: Obra – contratista principal | D21: Abono 1er contrato | E21: Germán Segura Rojas (CC 80.127.526) | F21: Abuelos – capital propio | G21: Efectivo retirado por el abuelo, entregado por Felipe | H21: Efectivo | I21: 5000000 | J21: Recibo firmado 15/09/2026 | K21: Soportado | L21: Gasto | M21: =IF(C21="","",IFERROR(VLOOKUP(C21,Supuestos!$A$58:$B$65,2,FALSE()),"Revisar")) -> Obra y adecuaciones
A22: 17 | B22: 46294 | C22: Obra – contratista principal | D22: Pago final de obra | E22: Germán Segura Rojas (CC 80.127.526) | F22: Préstamo mamá | G22: Andrés Felipe Fajardo — Nu ••6045 (dinero del préstamo transferido por mamá) | H22: Transferencia | I22: 1000000 | J22: Comprobante Nu 10694692…366546 | K22: Soportado | L22: Gasto | M22: =IF(C22="","",IFERROR(VLOOKUP(C22,Supuestos!$A$58:$B$65,2,FALSE()),"Revisar")) -> Obra y adecuaciones
A23: 18 | B23: 46294 | C23: Seguridad – cámaras | D23: Cámaras — pago 2 | E23: Oscar Mauricio Herrera Bello | F23: Préstamo mamá | G23: Andrés Felipe Fajardo — Nu ••6045 (dinero del préstamo transferido por mamá) | H23: Transferencia | I23: 1778650 | J23: Comprobante Nu 10893610…120247 | K23: Soportado | L23: Gasto | M23: =IF(C23="","",IFERROR(VLOOKUP(C23,Supuestos!$A$58:$B$65,2,FALSE()),"Revisar")) -> Obra y adecuaciones
A24: 19 | B24: 46295 | C24: Seguridad – cámaras | D24: Cámaras — pago 3 | E24: Oscar Mauricio Herrera Bello | F24: Préstamo mamá | G24: Janneth Quintero Ávila — Nu ••0510 | H24: Transferencia | I24: 1000000 | J24: Comprobante Nu 39673969…293348 | K24: Soportado | L24: Gasto | M24: =IF(C24="","",IFERROR(VLOOKUP(C24,Supuestos!$A$58:$B$65,2,FALSE()),"Revisar")) -> Obra y adecuaciones | N24: Total cámaras = cotización final $4.999.785
A25: 20 | C25: Traslado entre cuentas | D25: Sobrante del préstamo trasladado a la cuenta de la abuela (cuenta de la casa) | E25: Cuenta abuela | F25: Préstamo mamá | G25: Cuenta de mamá | H25: Transferencia | I25: 500215 | J25: Consultable en la app de la cuenta de la abuela | K25: Soportado | L25: Traslado | M25: =IF(C25="","",IFERROR(VLOOKUP(C25,Supuestos!$A$58:$B$65,2,FALSE()),"Revisar")) -> Traslado (no es gasto) | N25: Saldo = $35.000.000 − $29.500.000 − $4.999.785
A26: 21 | C26: Hidráulico – bomba de presión | D26: Bomba de presurización (equipo) | E26: Por confirmar | F26: TC abuelos (cuotas) | G26: Tarjeta de crédito abuelo | H26: Tarjeta de crédito | I26: 310000 | J26: Consultable en la app de la tarjeta del abuelo | K26: Soportado | L26: Gasto | M26: =IF(C26="","",IFERROR(VLOOKUP(C26,Supuestos!$A$58:$B$65,2,FALSE()),"Revisar")) -> Obra y adecuaciones
A27: 22 | B27: 46296 | C27: Hidráulico – bomba de presión | D27: Instalación bomba (mano de obra) | E27: Instalador | F27: Abuelos – capital propio | G27: Abuelo | H27: Por definir | I27: 300000 | J27: Pendiente | K27: Pendiente de pago | L27: Gasto | M27: =IF(C27="","",IFERROR(VLOOKUP(C27,Supuestos!$A$58:$B$65,2,FALSE()),"Revisar")) -> Obra y adecuaciones | N27: Instalación programada 1 oct 2026
A28: 23 | C28: Eléctrico – aumento de carga (Enel) | D28: Saldo adecuación eléctrica | E28: Clemente Gregorio Carriazo | F28: Abuelos – capital propio | G28: Abuelo | H28: Por definir | I28: 1250000 | J28: Pendiente | K28: Pendiente de pago | L28: Gasto | M28: =IF(C28="","",IFERROR(VLOOKUP(C28,Supuestos!$A$58:$B$65,2,FALSE()),"Revisar")) -> Obra y adecuaciones | N28: Obra civil terminada. Se paga cuando Enel cambie el contador y apruebe el aumento de carga
A29: 24 | C29: Mobiliario – habitaciones | D29: Amoblado completo habitación 1 (37 ítems — ver hoja Mobiliario) | E29: Mercado Libre (varias tiendas) | F29: TC abuelos (cuotas) | G29: Tarjeta de crédito abuelos | H29: Tarjeta de crédito | I29: =Mobiliario!B42 -> 6551800 | J29: Compras consultables en Mercado Libre y en la app de la tarjeta | K29: Soportado | L29: Gasto | M29: =IF(C29="","",IFERROR(VLOOKUP(C29,Supuestos!$A$58:$B$65,2,FALSE()),"Revisar")) -> Mobiliario | N29: Cuotas sin interés 6–12 meses. 1ª cuota (~$1.300.000) pagada con el arriendo de sep 2026
A30: =IF(C30="","",ROW()-5) | M30: =IF(C30="","",IFERROR(VLOOKUP(C30,Supuestos!$A$58:$B$65,2,FALSE()),"Revisar"))
A31: =IF(C31="","",ROW()-5) | M31: =IF(C31="","",IFERROR(VLOOKUP(C31,Supuestos!$A$58:$B$65,2,FALSE()),"Revisar"))
A32: =IF(C32="","",ROW()-5) | M32: =IF(C32="","",IFERROR(VLOOKUP(C32,Supuestos!$A$58:$B$65,2,FALSE()),"Revisar"))
A33: =IF(C33="","",ROW()-5) | M33: =IF(C33="","",IFERROR(VLOOKUP(C33,Supuestos!$A$58:$B$65,2,FALSE()),"Revisar"))
A34: =IF(C34="","",ROW()-5) | M34: =IF(C34="","",IFERROR(VLOOKUP(C34,Supuestos!$A$58:$B$65,2,FALSE()),"Revisar"))
A35: =IF(C35="","",ROW()-5) | M35: =IF(C35="","",IFERROR(VLOOKUP(C35,Supuestos!$A$58:$B$65,2,FALSE()),"Revisar"))
A36: =IF(C36="","",ROW()-5) | M36: =IF(C36="","",IFERROR(VLOOKUP(C36,Supuestos!$A$58:$B$65,2,FALSE()),"Revisar"))
A37: =IF(C37="","",ROW()-5) | M37: =IF(C37="","",IFERROR(VLOOKUP(C37,Supuestos!$A$58:$B$65,2,FALSE()),"Revisar"))
A38: =IF(C38="","",ROW()-5) | M38: =IF(C38="","",IFERROR(VLOOKUP(C38,Supuestos!$A$58:$B$65,2,FALSE()),"Revisar"))
A39: =IF(C39="","",ROW()-5) | M39: =IF(C39="","",IFERROR(VLOOKUP(C39,Supuestos!$A$58:$B$65,2,FALSE()),"Revisar"))
A40: =IF(C40="","",ROW()-5) | M40: =IF(C40="","",IFERROR(VLOOKUP(C40,Supuestos!$A$58:$B$65,2,FALSE()),"Revisar"))
A41: =IF(C41="","",ROW()-5) | M41: =IF(C41="","",IFERROR(VLOOKUP(C41,Supuestos!$A$58:$B$65,2,FALSE()),"Revisar"))
... A205: =IF(C205="","",ROW()-5) | M205: =IF(C205="","",IFERROR(VLOOKUP(C205,Supuestos!$A$58:$B$65,2,FALSE()),"Revisar"))

Sheet Cuadre
A1: Fuentes y usos del dinero — cuadre
A2: Todo sale de la hoja Movimientos. Si agrega un pago allá, este cuadre se actualiza solo.
A4: 1. ¿En qué se gastó y quién lo pagó? (incluye pagos pendientes)
A5: Categoría | B5: =Supuestos!$D$58 -> Abuelos – capital propio | C5: =Supuestos!$D$59 -> Préstamo mamá | D5: =Supuestos!$D$60 -> TC abuelos (cuotas) | E5: =Supuestos!$D$61 -> Arriendo de la casa | F5: =Supuestos!$D$62 -> Felipe (por definir) | G5: =Supuestos!$D$63 -> Por confirmar | H5: Total
A6: =Supuestos!$A$58 -> Obra – contratista principal | B6: =SUMIFS(Movimientos!$I$6:$I$205,Movimientos!$C$6:$C$205,$A6,Movimientos!$F$6:$F$205,B$5,Movimientos!$L$6:$L$205,"Gasto") -> 84500000 | C6: =SUMIFS(Movimientos!$I$6:$I$205,Movimientos!$C$6:$C$205,$A6,Movimientos!$F$6:$F$205,C$5,Movimientos!$L$6:$L$205,"Gasto") -> 29500000 | D6: =SUMIFS(Movimientos!$I$6:$I$205,Movimientos!$C$6:$C$205,$A6,Movimientos!$F$6:$F$205,D$5,Movimientos!$L$6:$L$205,"Gasto") -> 0 | E6: =SUMIFS(Movimientos!$I$6:$I$205,Movimientos!$C$6:$C$205,$A6,Movimientos!$F$6:$F$205,E$5,Movimientos!$L$6:$L$205,"Gasto") -> 0 | F6: =SUMIFS(Movimientos!$I$6:$I$205,Movimientos!$C$6:$C$205,$A6,Movimientos!$F$6:$F$205,F$5,Movimientos!$L$6:$L$205,"Gasto") -> 0 | G6: =SUMIFS(Movimientos!$I$6:$I$205,Movimientos!$C$6:$C$205,$A6,Movimientos!$F$6:$F$205,G$5,Movimientos!$L$6:$L$205,"Gasto") -> 0 | H6: =SUM(B6:G6) -> 114000000
A7: =Supuestos!$A$59 -> Costos bancarios – 4x1000 | B7: =SUMIFS(Movimientos!$I$6:$I$205,Movimientos!$C$6:$C$205,$A7,Movimientos!$F$6:$F$205,B$5,Movimientos!$L$6:$L$205,"Gasto") -> 80000 | C7: =SUMIFS(Movimientos!$I$6:$I$205,Movimientos!$C$6:$C$205,$A7,Movimientos!$F$6:$F$205,C$5,Movimientos!$L$6:$L$205,"Gasto") -> 16188 | D7: =SUMIFS(Movimientos!$I$6:$I$205,Movimientos!$C$6:$C$205,$A7,Movimientos!$F$6:$F$205,D$5,Movimientos!$L$6:$L$205,"Gasto") -> 0 | E7: =SUMIFS(Movimientos!$I$6:$I$205,Movimientos!$C$6:$C$205,$A7,Movimientos!$F$6:$F$205,E$5,Movimientos!$L$6:$L$205,"Gasto") -> 0 | F7: =SUMIFS(Movimientos!$I$6:$I$205,Movimientos!$C$6:$C$205,$A7,Movimientos!$F$6:$F$205,F$5,Movimientos!$L$6:$L$205,"Gasto") -> 0 | G7: =SUMIFS(Movimientos!$I$6:$I$205,Movimientos!$C$6:$C$205,$A7,Movimientos!$F$6:$F$205,G$5,Movimientos!$L$6:$L$205,"Gasto") -> 0 | H7: =SUM(B7:G7) -> 96188
A8: =Supuestos!$A$60 -> Eléctrico – aumento de carga (Enel) | B8: =SUMIFS(Movimientos!$I$6:$I$205,Movimientos!$C$6:$C$205,$A8,Movimientos!$F$6:$F$205,B$5,Movimientos!$L$6:$L$205,"Gasto") -> 5000000 | C8: =SUMIFS(Movimientos!$I$6:$I$205,Movimientos!$C$6:$C$205,$A8,Movimientos!$F$6:$F$205,C$5,Movimientos!$L$6:$L$205,"Gasto") -> 0 | D8: =SUMIFS(Movimientos!$I$6:$I$205,Movimientos!$C$6:$C$205,$A8,Movimientos!$F$6:$F$205,D$5,Movimientos!$L$6:$L$205,"Gasto") -> 0 | E8: =SUMIFS(Movimientos!$I$6:$I$205,Movimientos!$C$6:$C$205,$A8,Movimientos!$F$6:$F$205,E$5,Movimientos!$L$6:$L$205,"Gasto") -> 0 | F8: =SUMIFS(Movimientos!$I$6:$I$205,Movimientos!$C$6:$C$205,$A8,Movimientos!$F$6:$F$205,F$5,Movimientos!$L$6:$L$205,"Gasto") -> 0 | G8: =SUMIFS(Movimientos!$I$6:$I$205,Movimientos!$C$6:$C$205,$A8,Movimientos!$F$6:$F$205,G$5,Movimientos!$L$6:$L$205,"Gasto") -> 0 | H8: =SUM(B8:G8) -> 5000000
A9: =Supuestos!$A$61 -> Seguridad – cámaras | B9: =SUMIFS(Movimientos!$I$6:$I$205,Movimientos!$C$6:$C$205,$A9,Movimientos!$F$6:$F$205,B$5,Movimientos!$L$6:$L$205,"Gasto") -> 0 | C9: =SUMIFS(Movimientos!$I$6:$I$205,Movimientos!$C$6:$C$205,$A9,Movimientos!$F$6:$F$205,C$5,Movimientos!$L$6:$L$205,"Gasto") -> 4999785 | D9: =SUMIFS(Movimientos!$I$6:$I$205,Movimientos!$C$6:$C$205,$A9,Movimientos!$F$6:$F$205,D$5,Movimientos!$L$6:$L$205,"Gasto") -> 0 | E9: =SUMIFS(Movimientos!$I$6:$I$205,Movimientos!$C$6:$C$205,$A9,Movimientos!$F$6:$F$205,E$5,Movimientos!$L$6:$L$205,"Gasto") -> 0 | F9: =SUMIFS(Movimientos!$I$6:$I$205,Movimientos!$C$6:$C$205,$A9,Movimientos!$F$6:$F$205,F$5,Movimientos!$L$6:$L$205,"Gasto") -> 0 | G9: =SUMIFS(Movimientos!$I$6:$I$205,Movimientos!$C$6:$C$205,$A9,Movimientos!$F$6:$F$205,G$5,Movimientos!$L$6:$L$205,"Gasto") -> 0 | H9: =SUM(B9:G9) -> 4999785
A10: =Supuestos!$A$62 -> Hidráulico – bomba de presión | B10: =SUMIFS(Movimientos!$I$6:$I$205,Movimientos!$C$6:$C$205,$A10,Movimientos!$F$6:$F$205,B$5,Movimientos!$L$6:$L$205,"Gasto") -> 300000 | C10: =SUMIFS(Movimientos!$I$6:$I$205,Movimientos!$C$6:$C$205,$A10,Movimientos!$F$6:$F$205,C$5,Movimientos!$L$6:$L$205,"Gasto") -> 0 | D10: =SUMIFS(Movimientos!$I$6:$I$205,Movimientos!$C$6:$C$205,$A10,Movimientos!$F$6:$F$205,D$5,Movimientos!$L$6:$L$205,"Gasto") -> 310000 | E10: =SUMIFS(Movimientos!$I$6:$I$205,Movimientos!$C$6:$C$205,$A10,Movimientos!$F$6:$F$205,E$5,Movimientos!$L$6:$L$205,"Gasto") -> 0 | F10: =SUMIFS(Movimientos!$I$6:$I$205,Movimientos!$C$6:$C$205,$A10,Movimientos!$F$6:$F$205,F$5,Movimientos!$L$6:$L$205,"Gasto") -> 0 | G10: =SUMIFS(Movimientos!$I$6:$I$205,Movimientos!$C$6:$C$205,$A10,Movimientos!$F$6:$F$205,G$5,Movimientos!$L$6:$L$205,"Gasto") -> 0 | H10: =SUM(B10:G10) -> 610000
A11: =Supuestos!$A$63 -> Mobiliario – habitaciones | B11: =SUMIFS(Movimientos!$I$6:$I$205,Movimientos!$C$6:$C$205,$A11,Movimientos!$F$6:$F$205,B$5,Movimientos!$L$6:$L$205,"Gasto") -> 0 | C11: =SUMIFS(Movimientos!$I$6:$I$205,Movimientos!$C$6:$C$205,$A11,Movimientos!$F$6:$F$205,C$5,Movimientos!$L$6:$L$205,"Gasto") -> 0 | D11: =SUMIFS(Movimientos!$I$6:$I$205,Movimientos!$C$6:$C$205,$A11,Movimientos!$F$6:$F$205,D$5,Movimientos!$L$6:$L$205,"Gasto") -> 6551800 | E11: =SUMIFS(Movimientos!$I$6:$I$205,Movimientos!$C$6:$C$205,$A11,Movimientos!$F$6:$F$205,E$5,Movimientos!$L$6:$L$205,"Gasto") -> 0 | F11: =SUMIFS(Movimientos!$I$6:$I$205,Movimientos!$C$6:$C$205,$A11,Movimientos!$F$6:$F$205,F$5,Movimientos!$L$6:$L$205,"Gasto") -> 0 | G11: =SUMIFS(Movimientos!$I$6:$I$205,Movimientos!$C$6:$C$205,$A11,Movimientos!$F$6:$F$205,G$5,Movimientos!$L$6:$L$205,"Gasto") -> 0 | H11: =SUM(B11:G11) -> 6551800
A12: =Supuestos!$A$64 -> Lavandería – lavadora | B12: =SUMIFS(Movimientos!$I$6:$I$205,Movimientos!$C$6:$C$205,$A12,Movimientos!$F$6:$F$205,B$5,Movimientos!$L$6:$L$205,"Gasto") -> 0 | C12: =SUMIFS(Movimientos!$I$6:$I$205,Movimientos!$C$6:$C$205,$A12,Movimientos!$F$6:$F$205,C$5,Movimientos!$L$6:$L$205,"Gasto") -> 0 | D12: =SUMIFS(Movimientos!$I$6:$I$205,Movimientos!$C$6:$C$205,$A12,Movimientos!$F$6:$F$205,D$5,Movimientos!$L$6:$L$205,"Gasto") -> 0 | E12: =SUMIFS(Movimientos!$I$6:$I$205,Movimientos!$C$6:$C$205,$A12,Movimientos!$F$6:$F$205,E$5,Movimientos!$L$6:$L$205,"Gasto") -> 0 | F12: =SUMIFS(Movimientos!$I$6:$I$205,Movimientos!$C$6:$C$205,$A12,Movimientos!$F$6:$F$205,F$5,Movimientos!$L$6:$L$205,"Gasto") -> 0 | G12: =SUMIFS(Movimientos!$I$6:$I$205,Movimientos!$C$6:$C$205,$A12,Movimientos!$F$6:$F$205,G$5,Movimientos!$L$6:$L$205,"Gasto") -> 0 | H12: =SUM(B12:G12) -> 0
A13: TOTAL | B13: =SUM(B6:B12) -> 89880000 | C13: =SUM(C6:C12) -> 34515973 | D13: =SUM(D6:D12) -> 6861800 | E13: =SUM(E6:E12) -> 0 | F13: =SUM(F6:F12) -> 0 | G13: =SUM(G6:G12) -> 0 | H13: =SUM(H6:H12) -> 131257773
A14: Control: total cuadre = total Movimientos | H14: =IF(ROUND(H13-Movimientos!$I$4,0)=0,"OK","REVISAR") -> OK
A17: 2. Préstamo de mamá — ¿a dónde fue cada peso?
A18: Monto recibido | B18: =Supuestos!$B$32 -> 35000000
A19: Pagado a proveedores (contratista y cámaras) | B19: =SUMIFS(Movimientos!$I$6:$I$205,Movimientos!$F$6:$F$205,"Préstamo mamá",Movimientos!$L$6:$L$205,"Gasto",Movimientos!$C$6:$C$205,"<>Costos bancarios – 4x1000") -> 34499785 | C19: Aparte: 4x1000 asumido por la cuenta de mamá, adicional al préstamo: | H19: =SUMIFS(Movimientos!$I$6:$I$205,Movimientos!$F$6:$F$205,"Préstamo mamá",Movimientos!$C$6:$C$205,"Costos bancarios – 4x1000") -> 16188
A20: Trasladado a la cuenta de la abuela | B20: =SUMIFS(Movimientos!$I$6:$I$205,Movimientos!$F$6:$F$205,"Préstamo mamá",Movimientos!$L$6:$L$205,"Traslado") -> 500215
A21: Diferencia sin explicar (debe ser 0) | B21: =B18-B19-B20 -> 0
A23: 3. Contratista principal — contratado vs. pagado
A24: Contrato inicial | B24: 85000000 | C24: Abuelo: $84.500.000 · Préstamo mamá: $29.500.000
A25: Acuerdo de arreglos adicionales | B25: 29000000
A26: Total contratado | B26: =B24+B25 -> 114000000
A27: Total pagado (12 pagos: 5 recibos en efectivo + 7 transferencias) | B27: =SUMIFS(Movimientos!$I$6:$I$205,Movimientos!$C$6:$C$205,"Obra – contratista principal",Movimientos!$L$6:$L$205,"Gasto") -> 114000000
A28: Saldo por pagar al contratista | B28: =B26-B27 -> 0
A30: 4. Pagado vs. pendiente
A31: Ya pagado | B31: =SUMIFS(Movimientos!$I$6:$I$205,Movimientos!$L$6:$L$205,"Gasto",Movimientos!$K$6:$K$205,"<>Pendiente de pago") -> 129707773
A32: Pendiente de pago (saldo eléctrico + mano de obra bomba) | B32: =SUMIFS(Movimientos!$I$6:$I$205,Movimientos!$L$6:$L$205,"Gasto",Movimientos!$K$6:$K$205,"Pendiente de pago") -> 1550000
A33: Total | B33: =B31+B32 -> 131257773
A35: 5. Tarjeta de crédito de los abuelos
A36: Compras cargadas a la tarjeta (mobiliario + bomba) | B36: =SUMIFS(Movimientos!$I$6:$I$205,Movimientos!$F$6:$F$205,"TC abuelos (cuotas)",Movimientos!$L$6:$L$205,"Gasto") -> 6861800
A37: Cuotas pagadas (según Registro Mensual) | B37: =SUM('Registro Mensual'!$K$6:$K$41) -> 1190248
A38: Saldo pendiente en la tarjeta | B38: =B36-B37 -> 5671552
A40: 6. Pendiente: aportes de Felipe
A41: Pagos registrados desde la cuenta de Felipe con fuente 'Felipe (por definir)' | B41: =SUMIFS(Movimientos!$I$6:$I$205,Movimientos!$F$6:$F$205,"Felipe (por definir)",Movimientos!$L$6:$L$205,"Gasto") -> 0
A42: Además, Felipe pagó con su cuenta y tarjetas otras compras de la casa. Se documentarán con extractos bancarios y se definirá si son reembolso o aporte.

Sheet Mobiliario
A1: Mobiliario por habitación
A2: Hab 1 = costo real pagado. Hab 2–7: escriba el costo real de cada ítem al comprarlo. Mientras una habitación no tenga datos, se usa el costo de la Hab 1 como estimado.
A4: Ítem | B4: Hab 1 (real) | C4: Hab 2 | D4: Hab 3 | E4: Hab 4 | F4: Hab 5 | G4: Hab 6 | H4: Hab 7
A5: Ducha | B5: 172200
A6: Gabinete de baño | B6: 139900
A7: Bowl acero inoxidable | B7: 12400
A8: Tijeras de cocina | B8: 15600
A9: Estantería de ducha | B9: 28000
A10: Basurero de pedal 20 litros | B10: 70500
A11: Microondas Electrolux | B11: 250000
A12: Vajilla 2 puestos Corona | B12: 52000
A13: Set de cubiertos en acero | B13: 20000
A14: Nevera minibar | B14: 620000
A15: Filtro de agua ozono | B15: 180000
A16: Cobijas x2 | B16: 80000
... A41: Mesa abatible multiusos para cocina | B41: 169000
A42: Total registrado (real) | B42: =SUM(B5:B41) -> 6551800 | C42: =SUM(C5:C41) -> 0 | D42: =SUM(D5:D41) -> 0 | E42: =SUM(E5:E41) -> 0 | F42: =SUM(F5:F41) -> 0 | G42: =SUM(G5:G41) -> 0 | H42: =SUM(H5:H41) -> 0
A43: ¿Real o estimado? | B43: =IF(B42>0,"Real","Estimado") -> Real | C43: =IF(C42>0,"Real","Estimado") -> Estimado | D43: =IF(D42>0,"Real","Estimado") -> Estimado | E43: =IF(E42>0,"Real","Estimado") -> Estimado | F43: =IF(F42>0,"Real","Estimado") -> Estimado | G43: =IF(G42>0,"Real","Estimado") -> Estimado | H43: =IF(H42>0,"Real","Estimado") -> Estimado
A44: Costo usado en los cálculos | B44: =B42 -> 6551800 | C44: =IF(C42>0,C42,$B$42*IF(Supuestos!$B$7="Pequeña",Supuestos!$B$44,1)) -> 6551800 | D44: =IF(D42>0,D42,$B$42*IF(Supuestos!$B$8="Pequeña",Supuestos!$B$44,1)) -> 6551800 | E44: =IF(E42>0,E42,$B$42*IF(Supuestos!$B$9="Pequeña",Supuestos!$B$44,1)) -> 6551800 | F44: =IF(F42>0,F42,$B$42*IF(Supuestos!$B$10="Pequeña",Supuestos!$B$44,1)) -> 6551800 | G44: =IF(G42>0,G42,$B$42*IF(Supuestos!$B$11="Pequeña",Supuestos!$B$44,1)) -> 6551800 | H44: =IF(H42>0,H42,$B$42*IF(Supuestos!$B$12="Pequeña",Supuestos!$B$44,1)) -> 6551800
A45: Total mobiliario 7 habitaciones | B45: =SUM(B44:H44) -> 45862600
A48: Lavandería — lavadora nueva y monedero
A49: Opción | B49: Precio | C49: Nota
A50: Whirlpool 14 kg | B50: 2830000 | C50: Cotizada por Felipe
A51: Whirlpool 20 kg | B51: 3350000 | C51: Cotizada por Felipe — permite lavar cobijas y edredones
A52: Opción seleccionada (escriba 1 = 14 kg, 2 = 20 kg) | B52: 1 | C52: =INDEX(B50:B51,B52) -> 2830000
A54: Monedero para cobro por ciclo | B54: 1190000 | C54: Cotizado por Felipe — ordena el uso y genera ingreso por ciclo
A56: ¿Incluir monedero? (1 = sí, 0 = no) | B56: 1
A57: TOTAL LAVANDERÍA | C57: =C52+B54*B56 -> 4020000
A59: Lavadora actual: Whirlpool de más de 20 años, alto consumo de energía. Zonas comunes ya amobladas (a mediano plazo: puffs o sillas de lectura).

Sheet Préstamo
A1: Préstamo de mamá — tabla de amortización (sistema francés)
A2: Intereses de gracia se suman al capital; cuota fija desde el 15 dic 2026. Columnas J–K: registre cada pago real.
A3: Monto prestado | B3: =Supuestos!$B$32 -> 35000000
A4: Tasa nominal mensual | B4: =Supuestos!$B$33 -> 0.015
A5: Tasa efectiva anual equivalente | B5: =(1+B4)^12-1 -> 0.19561817
A6: Fecha de desembolso | B6: =Supuestos!$B$34 -> 46249
A7: Fecha primera cuota | B7: =Supuestos!$B$35 -> 46371
A8: Número de cuotas | B8: =Supuestos!$B$36 -> 36
A9: Meses de interés sumado al capital antes del primer periodo | B9: =(YEAR(B7)-YEAR(B6))*12+MONTH(B7)-MONTH(B6)-1 -> 3
A10: Saldo sobre el que se calculan las cuotas | B10: =B3*(1+B4)^B9 -> 36598743
A11: Cuota fija mensual | B11: =PMT(B4,B8,-B10) -> 1323132.2
A12: Total a pagar en 36 cuotas | B12: =B11*B8 -> 47632761
A13: Total intereses si se paga en cuotas | B13: =B12-B3 -> 12632761
A17: N° | B17: Fecha | C17: Mes | D17: Tipo | E17: Saldo inicial | F17: Interés | G17: Cuota | H17: Abono a capital | I17: Saldo final | J17: Pagado real | K17: Fecha pago real | L17: Nota
A18: 0 | B18: =EDATE($B$6,A18) -> 46249 | C18: =DATE(YEAR(B18),MONTH(B18),1) -> 46235 | D18: =IF(A18=0,"Desembolso",IF(B18<$B$7,"Gracia (interés se suma)","Cuota "&(A18-$B$9))) -> Desembolso | E18: 0 | F18: 0 | G18: 0 | H18: =G18-F18 -> 0 | I18: =$B$3 -> 35000000
A19: 1 | B19: =EDATE($B$6,A19) -> 46280 | C19: =DATE(YEAR(B19),MONTH(B19),1) -> 46266 | D19: =IF(A19=0,"Desembolso",IF(B19<$B$7,"Gracia (interés se suma)","Cuota "&(A19-$B$9))) -> Gracia (interés se suma) | E19: =I18 -> 35000000 | F19: =E19*$B$4 -> 525000 | G19: =IF(B19>=$B$7,$B$11,0) -> 0 | H19: =G19-F19 -> -525000 | I19: =MAX(0,ROUND(E19+F19-G19,0)) -> 35525000
A20: 2 | B20: =EDATE($B$6,A20) -> 46310 | C20: =DATE(YEAR(B20),MONTH(B20),1) -> 46296 | D20: =IF(A20=0,"Desembolso",IF(B20<$B$7,"Gracia (interés se suma)","Cuota "&(A20-$B$9))) -> Gracia (interés se suma) | E20: =I19 -> 35525000 | F20: =E20*$B$4 -> 532875 | G20: =IF(B20>=$B$7,$B$11,0) -> 0 | H20: =G20-F20 -> -532875 | I20: =MAX(0,ROUND(E20+F20-G20,0)) -> 36057875
A21: 3 | B21: =EDATE($B$6,A21) -> 46341 | C21: =DATE(YEAR(B21),MONTH(B21),1) -> 46327 | D21: =IF(A21=0,"Desembolso",IF(B21<$B$7,"Gracia (interés se suma)","Cuota "&(A21-$B$9))) -> Gracia (interés se suma) | E21: =I20 -> 36057875 | F21: =E21*$B$4 -> 540868.12 | G21: =IF(B21>=$B$7,$B$11,0) -> 0 | H21: =G21-F21 -> -540868.12 | I21: =MAX(0,ROUND(E21+F21-G21,0)) -> 36598743
A22: 4 | B22: =EDATE($B$6,A22) -> 46371 | C22: =DATE(YEAR(B22),MONTH(B22),1) -> 46357 | D22: =IF(A22=0,"Desembolso",IF(B22<$B$7,"Gracia (interés se suma)","Cuota "&(A22-$B$9))) -> Cuota 1 | E22: =I21 -> 36598743 | F22: =E22*$B$4 -> 548981.15 | G22: =IF(B22>=$B$7,$B$11,0) -> 1323132.2 | H22: =G22-F22 -> 774151.09 | I22: =MAX(0,ROUND(E22+F22-G22,0)) -> 35824592
A23: 5 | B23: =EDATE($B$6,A23) -> 46402 | C23: =DATE(YEAR(B23),MONTH(B23),1) -> 46388 | D23: =IF(A23=0,"Desembolso",IF(B23<$B$7,"Gracia (interés se suma)","Cuota "&(A23-$B$9))) -> Cuota 2 | E23: =I22 -> 35824592 | F23: =E23*$B$4 -> 537368.88 | G23: =IF(B23>=$B$7,$B$11,0) -> 1323132.2 | H23: =G23-F23 -> 785763.36 | I23: =MAX(0,ROUND(E23+F23-G23,0)) -> 35038829
A24: 6 | B24: =EDATE($B$6,A24) -> 46433 | C24: =DATE(YEAR(B24),MONTH(B24),1) -> 46419 | D24: =IF(A24=0,"Desembolso",IF(B24<$B$7,"Gracia (interés se suma)","Cuota "&(A24-$B$9))) -> Cuota 3 | E24: =I23 -> 35038829 | F24: =E24*$B$4 -> 525582.44 | G24: =IF(B24>=$B$7,$B$11,0) -> 1323132.2 | H24: =G24-F24 -> 797549.8 | I24: =MAX(0,ROUND(E24+F24-G24,0)) -> 34241279
A25: 7 | B25: =EDATE($B$6,A25) -> 46461 | C25: =DATE(YEAR(B25),MONTH(B25),1) -> 46447 | D25: =IF(A25=0,"Desembolso",IF(B25<$B$7,"Gracia (interés se suma)","Cuota "&(A25-$B$9))) -> Cuota 4 | E25: =I24 -> 34241279 | F25: =E25*$B$4 -> 513619.18 | G25: =IF(B25>=$B$7,$B$11,0) -> 1323132.2 | H25: =G25-F25 -> 809513.05 | I25: =MAX(0,ROUND(E25+F25-G25,0)) -> 33431766
A26: 8 | B26: =EDATE($B$6,A26) -> 46492 | C26: =DATE(YEAR(B26),MONTH(B26),1) -> 46478 | D26: =IF(A26=0,"Desembolso",IF(B26<$B$7,"Gracia (interés se suma)","Cuota "&(A26-$B$9))) -> Cuota 5 | E26: =I25 -> 33431766 | F26: =E26*$B$4 -> 501476.49 | G26: =IF(B26>=$B$7,$B$11,0) -> 1323132.2 | H26: =G26-F26 -> 821655.75 | I26: =MAX(0,ROUND(E26+F26-G26,0)) -> 32610110
A27: 9 | B27: =EDATE($B$6,A27) -> 46522 | C27: =DATE(YEAR(B27),MONTH(B27),1) -> 46508 | D27: =IF(A27=0,"Desembolso",IF(B27<$B$7,"Gracia (interés se suma)","Cuota "&(A27-$B$9))) -> Cuota 6 | E27: =I26 -> 32610110 | F27: =E27*$B$4 -> 489151.65 | G27: =IF(B27>=$B$7,$B$11,0) -> 1323132.2 | H27: =G27-F27 -> 833980.59 | I27: =MAX(0,ROUND(E27+F27-G27,0)) -> 31776129
A28: 10 | B28: =EDATE($B$6,A28) -> 46553 | C28: =DATE(YEAR(B28),MONTH(B28),1) -> 46539 | D28: =IF(A28=0,"Desembolso",IF(B28<$B$7,"Gracia (interés se suma)","Cuota "&(A28-$B$9))) -> Cuota 7 | E28: =I27 -> 31776129 | F28: =E28*$B$4 -> 476641.93 | G28: =IF(B28>=$B$7,$B$11,0) -> 1323132.2 | H28: =G28-F28 -> 846490.3 | I28: =MAX(0,ROUND(E28+F28-G28,0)) -> 30929639
A29: 11 | B29: =EDATE($B$6,A29) -> 46583 | C29: =DATE(YEAR(B29),MONTH(B29),1) -> 46569 | D29: =IF(A29=0,"Desembolso",IF(B29<$B$7,"Gracia (interés se suma)","Cuota "&(A29-$B$9))) -> Cuota 8 | E29: =I28 -> 30929639 | F29: =E29*$B$4 -> 463944.59 | G29: =IF(B29>=$B$7,$B$11,0) -> 1323132.2 | H29: =G29-F29 -> 859187.65 | I29: =MAX(0,ROUND(E29+F29-G29,0)) -> 30070451
A30: 12 | B30: =EDATE($B$6,A30) -> 46614 | C30: =DATE(YEAR(B30),MONTH(B30),1) -> 46600 | D30: =IF(A30=0,"Desembolso",IF(B30<$B$7,"Gracia (interés se suma)","Cuota "&(A30-$B$9))) -> Cuota 9 | E30: =I29 -> 30070451 | F30: =E30*$B$4 -> 451056.77 | G30: =IF(B30>=$B$7,$B$11,0) -> 1323132.2 | H30: =G30-F30 -> 872075.47 | I30: =MAX(0,ROUND(E30+F30-G30,0)) -> 29198376
... A57: 39 | B57: =EDATE($B$6,A57) -> 47437 | C57: =DATE(YEAR(B57),MONTH(B57),1) -> 47423 | D57: =IF(A57=0,"Desembolso",IF(B57<$B$7,"Gracia (interés se suma)","Cuota "&(A57-$B$9))) -> Cuota 36 | E57: =I56 -> 1303579 | F57: =E57*$B$4 -> 19553.685 | G57: =IF(B57>=$B$7,$B$11,0) -> 1323132.2 | H57: =G57-F57 -> 1303578.6 | I57: =MAX(0,ROUND(E57+F57-G57,0)) -> 0

Sheet Registro Mensual
A1: Registro mensual real — documento vivo
A2: Cada mes: escriba en azul lo que realmente entró y salió. La columna 'Proyectado' compara contra el plan.
A5: Mes | B5: Hab. ocupadas | C5: Arriendos cobrados | D5: Servicios pagados | E5: Reserva apartada | F5: Predial apartado | G5: Neto operativo | H5: Comisión administración | I5: Neto casa (antes de deudas) | J5: Cuota préstamo pagada | K5: Cuotas tarjeta pagadas con arriendo | L5: Neto entregado a los abuelos | M5: Neto proyectado (antes de deudas) | N5: Diferencia real − proyectado | O5: Notas
A6: 46266 | B6: 1 | C6: 1250000 | D6: 606000 | E6: 0 | F6: 0 | G6: =IF(C6="","",C6-D6-E6-F6) -> 644000 | H6: =IF(G6="","",MAX(0,G6)*Supuestos!$B$28) -> 128800 | I6: =IF(G6="","",G6-H6) -> 515200 | J6: 0 | K6: 1190248 | L6: =IF(I6="","",I6-J6-K6) -> -675048 | M6: =IFERROR(INDEX('Flujo Proyectado'!$I$6:$I$77,MATCH(A6,'Flujo Proyectado'!$A$6:$A$77,0)),"") | N6: =IF(OR(I6="",M6=""),"",I6-M6) | O6: Arriendo Hab 1 se usó completo para la 1ª cuota de la tarjeta (muebles). Servicios = valores actuales reportados. Comisión causada, no cobrada. Nadie recibió ganancia.
A7: =EDATE(A6,1) -> 46296 | G7: =IF(C7="","",C7-D7-E7-F7) | H7: =IF(G7="","",MAX(0,G7)*Supuestos!$B$28) | I7: =IF(G7="","",G7-H7) | L7: =IF(I7="","",I7-J7-K7) | M7: =IFERROR(INDEX('Flujo Proyectado'!$I$6:$I$77,MATCH(A7,'Flujo Proyectado'!$A$6:$A$77,0)),"") -> 320266.67 | N7: =IF(OR(I7="",M7=""),"",I7-M7)
A8: =EDATE(A7,1) -> 46327 | G8: =IF(C8="","",C8-D8-E8-F8) | H8: =IF(G8="","",MAX(0,G8)*Supuestos!$B$28) | I8: =IF(G8="","",G8-H8) | L8: =IF(I8="","",I8-J8-K8) | M8: =IFERROR(INDEX('Flujo Proyectado'!$I$6:$I$77,MATCH(A8,'Flujo Proyectado'!$A$6:$A$77,0)),"") -> 1967520 | N8: =IF(OR(I8="",M8=""),"",I8-M8)
A9: =EDATE(A8,1) -> 46357 | G9: =IF(C9="","",C9-D9-E9-F9) | H9: =IF(G9="","",MAX(0,G9)*Supuestos!$B$28) | I9: =IF(G9="","",G9-H9) | L9: =IF(I9="","",I9-J9-K9) | M9: =IFERROR(INDEX('Flujo Proyectado'!$I$6:$I$77,MATCH(A9,'Flujo Proyectado'!$A$6:$A$77,0)),"") -> 2731146.7 | N9: =IF(OR(I9="",M9=""),"",I9-M9)
A10: =EDATE(A9,1) -> 46388 | G10: =IF(C10="","",C10-D10-E10-F10) | H10: =IF(G10="","",MAX(0,G10)*Supuestos!$B$28) | I10: =IF(G10="","",G10-H10) | L10: =IF(I10="","",I10-J10-K10) | M10: =IFERROR(INDEX('Flujo Proyectado'!$I$6:$I$77,MATCH(A10,'Flujo Proyectado'!$A$6:$A$77,0)),"") -> 3294773.3 | N10: =IF(OR(I10="",M10=""),"",I10-M10)
A11: =EDATE(A10,1) -> 46419 | G11: =IF(C11="","",C11-D11-E11-F11) | H11: =IF(G11="","",MAX(0,G11)*Supuestos!$B$28) | I11: =IF(G11="","",G11-H11) | L11: =IF(I11="","",I11-J11-K11) | M11: =IFERROR(INDEX('Flujo Proyectado'!$I$6:$I$77,MATCH(A11,'Flujo Proyectado'!$A$6:$A$77,0)),"") -> 3858400 | N11: =IF(OR(I11="",M11=""),"",I11-M11)
A12: =EDATE(A11,1) -> 46447 | G12: =IF(C12="","",C12-D12-E12-F12) | H12: =IF(G12="","",MAX(0,G12)*Supuestos!$B$28) | I12: =IF(G12="","",G12-H12) | L12: =IF(I12="","",I12-J12-K12) | M12: =IFERROR(INDEX('Flujo Proyectado'!$I$6:$I$77,MATCH(A12,'Flujo Proyectado'!$A$6:$A$77,0)),"") -> 3858400 | N12: =IF(OR(I12="",M12=""),"",I12-M12)
A13: =EDATE(A12,1) -> 46478 | G13: =IF(C13="","",C13-D13-E13-F13) | H13: =IF(G13="","",MAX(0,G13)*Supuestos!$B$28) | I13: =IF(G13="","",G13-H13) | L13: =IF(I13="","",I13-J13-K13) | M13: =IFERROR(INDEX('Flujo Proyectado'!$I$6:$I$77,MATCH(A13,'Flujo Proyectado'!$A$6:$A$77,0)),"") -> 3858400 | N13: =IF(OR(I13="",M13=""),"",I13-M13)
A14: =EDATE(A13,1) -> 46508 | G14: =IF(C14="","",C14-D14-E14-F14) | H14: =IF(G14="","",MAX(0,G14)*Supuestos!$B$28) | I14: =IF(G14="","",G14-H14) | L14: =IF(I14="","",I14-J14-K14) | M14: =IFERROR(INDEX('Flujo Proyectado'!$I$6:$I$77,MATCH(A14,'Flujo Proyectado'!$A$6:$A$77,0)),"") -> 3858400 | N14: =IF(OR(I14="",M14=""),"",I14-M14)
A15: =EDATE(A14,1) -> 46539 | G15: =IF(C15="","",C15-D15-E15-F15) | H15: =IF(G15="","",MAX(0,G15)*Supuestos!$B$28) | I15: =IF(G15="","",G15-H15) | L15: =IF(I15="","",I15-J15-K15) | M15: =IFERROR(INDEX('Flujo Proyectado'!$I$6:$I$77,MATCH(A15,'Flujo Proyectado'!$A$6:$A$77,0)),"") -> 3858400 | N15: =IF(OR(I15="",M15=""),"",I15-M15)
A16: =EDATE(A15,1) -> 46569 | G16: =IF(C16="","",C16-D16-E16-F16) | H16: =IF(G16="","",MAX(0,G16)*Supuestos!$B$28) | I16: =IF(G16="","",G16-H16) | L16: =IF(I16="","",I16-J16-K16) | M16: =IFERROR(INDEX('Flujo Proyectado'!$I$6:$I$77,MATCH(A16,'Flujo Proyectado'!$A$6:$A$77,0)),"") -> 3858400 | N16: =IF(OR(I16="",M16=""),"",I16-M16)
A17: =EDATE(A16,1) -> 46600 | G17: =IF(C17="","",C17-D17-E17-F17) | H17: =IF(G17="","",MAX(0,G17)*Supuestos!$B$28) | I17: =IF(G17="","",G17-H17) | L17: =IF(I17="","",I17-J17-K17) | M17: =IFERROR(INDEX('Flujo Proyectado'!$I$6:$I$77,MATCH(A17,'Flujo Proyectado'!$A$6:$A$77,0)),"") -> 3858400 | N17: =IF(OR(I17="",M17=""),"",I17-M17)
A18: =EDATE(A17,1) -> 46631 | G18: =IF(C18="","",C18-D18-E18-F18) | H18: =IF(G18="","",MAX(0,G18)*Supuestos!$B$28) | I18: =IF(G18="","",G18-H18) | L18: =IF(I18="","",I18-J18-K18) | M18: =IFERROR(INDEX('Flujo Proyectado'!$I$6:$I$77,MATCH(A18,'Flujo Proyectado'!$A$6:$A$77,0)),"") -> 3858400 | N18: =IF(OR(I18="",M18=""),"",I18-M18)
... A41: =EDATE(A40,1) -> 47331 | G41: =IF(C41="","",C41-D41-E41-F41) | H41: =IF(G41="","",MAX(0,G41)*Supuestos!$B$28) | I41: =IF(G41="","",G41-H41) | L41: =IF(I41="","",I41-J41-K41) | M41: =IFERROR(INDEX('Flujo Proyectado'!$I$6:$I$77,MATCH(A41,'Flujo Proyectado'!$A$6:$A$77,0)),"") -> 4662026.7 | N41: =IF(OR(I41="",M41=""),"",I41-M41)

Sheet Flujo Proyectado
A1: Flujo proyectado mes a mes — 72 meses
A2: Llenado gradual según fechas de ingreso (hoja Supuestos). En ambas opciones el arriendo paga la operación y la cuota del préstamo de mamá. La diferencia es de dónde salen las cuotas de los muebles.
A4: OPERACIÓN DE LA CASA | J4: OPCIÓN A — el arriendo paga también los muebles | N4: OPCIÓN B — los ahorros pagan los muebles | R4: RECUPERACIÓN ACUMULADA POR COMISIÓN
A5: Mes | B5: Hab. ocupadas | C5: Ingreso bruto (arriendos + lavandería) | D5: Servicios | E5: Reserva reparac. + vacancia | F5: Ahorro predial | G5: Neto operativo | H5: Comisión administración | I5: Neto casa (antes de deudas) | J5: Cuota préstamo mamá | K5: Cuotas muebles + lavadora | L5: Caja casa A | M5: Acumulado A | N5: Caja casa B | O5: Acumulado B | P5: Tomado de ahorros (muebles − venta objetos) | Q5: Acumulado tomado de ahorros | R5: Acum. neto 10% | S5: Acum. neto 20% | T5: Acum. neto 30%
A6: =Supuestos!$B$54 -> 46296 | B6: =SUMPRODUCT(--(Supuestos!$D$6:$D$12<=A6)) -> 1 | C6: =SUMPRODUCT((Supuestos!$D$6:$D$12<=A6)*Supuestos!$C$6:$C$12)+IF(A6>=Supuestos!$F$31,B6*Supuestos!$F$30*Supuestos!$F$29*Supuestos!$F$32,0) -> 1278000 | D6: =IF(B6=0,0,Supuestos!$B$22+(Supuestos!$C$22-Supuestos!$B$22)*(B6-1)/(Supuestos!$F$33-1))-IF(A6>=Supuestos!$B$46,Supuestos!$B$47,0) -> 561000 | E6: =Supuestos!$C$23*B6/Supuestos!$F$33 -> 216666.67 | F6: =Supuestos!$C$24 -> 100000 | G6: =C6-D6-E6-F6 -> 400333.33 | H6: =MAX(0,G6)*Supuestos!$B$28 -> 80066.667 | I6: =G6-H6 -> 320266.67 | J6: =IFERROR(INDEX(Préstamo!$G$18:$G$57,MATCH(A6,Préstamo!$C$18:$C$57,0)),0) -> 0 | K6: =SUMPRODUCT((Supuestos!$G$6:$G$12<=A6)*(Supuestos!$H$6:$H$12>=A6)*Supuestos!$I$6:$I$12)/Supuestos!$B$43+IF(AND(A6>=Supuestos!$B$46,A6<=EDATE(Supuestos!$B$46,Supuestos!$B$43-1)),Supuestos!$B$45/Supuestos!$B$43,0) -> 2140450 | L6: =I6-J6-K6 -> -1820183.3 | M6: =L6 -> -1820183.3 | N6: =I6-J6 -> 320266.67 | O6: =N6 -> 320266.67 | P6: =K6-IF(A6=Supuestos!$F$35,Supuestos!$F$28,0) -> 2140450 | Q6: =P6 -> 2140450 | R6: =(G6-MAX(0,G6)*Supuestos!$B$29) -> 360300 | S6: =(G6-MAX(0,G6)*Supuestos!$B$30) -> 320266.67 | T6: =(G6-MAX(0,G6)*Supuestos!$B$31) -> 280233.33
A7: =EDATE(A6,1) -> 46327 | B7: =SUMPRODUCT(--(Supuestos!$D$6:$D$12<=A7)) -> 3 | C7: =SUMPRODUCT((Supuestos!$D$6:$D$12<=A7)*Supuestos!$C$6:$C$12)+IF(A7>=Supuestos!$F$31,B7*Supuestos!$F$30*Supuestos!$F$29*Supuestos!$F$32,0) -> 4184000 | D7: =IF(B7=0,0,Supuestos!$B$22+(Supuestos!$C$22-Supuestos!$B$22)*(B7-1)/(Supuestos!$F$33-1))-IF(A7>=Supuestos!$B$46,Supuestos!$B$47,0) -> 974600 | E7: =Supuestos!$C$23*B7/Supuestos!$F$33 -> 650000 | F7: =Supuestos!$C$24 -> 100000 | G7: =C7-D7-E7-F7 -> 2459400 | H7: =MAX(0,G7)*Supuestos!$B$28 -> 491880 | I7: =G7-H7 -> 1967520 | J7: =IFERROR(INDEX(Préstamo!$G$18:$G$57,MATCH(A7,Préstamo!$C$18:$C$57,0)),0) -> 0 | K7: =SUMPRODUCT((Supuestos!$G$6:$G$12<=A7)*(Supuestos!$H$6:$H$12>=A7)*Supuestos!$I$6:$I$12)/Supuestos!$B$43+IF(AND(A7>=Supuestos!$B$46,A7<=EDATE(Supuestos!$B$46,Supuestos!$B$43-1)),Supuestos!$B$45/Supuestos!$B$43,0) -> 2959425 | L7: =I7-J7-K7 -> -991905 | M7: =M6+L7 -> -2812088.3 | N7: =I7-J7 -> 1967520 | O7: =O6+N7 -> 2287786.7 | P7: =K7-IF(A7=Supuestos!$F$35,Supuestos!$F$28,0) -> 2959425 | Q7: =Q6+P7 -> 5099875 | R7: =R6+(G7-MAX(0,G7)*Supuestos!$B$29) -> 2573760 | S7: =S6+(G7-MAX(0,G7)*Supuestos!$B$30) -> 2287786.7 | T7: =T6+(G7-MAX(0,G7)*Supuestos!$B$31) -> 2001813.3
A8: =EDATE(A7,1) -> 46357 | B8: =SUMPRODUCT(--(Supuestos!$D$6:$D$12<=A8)) -> 4 | C8: =SUMPRODUCT((Supuestos!$D$6:$D$12<=A8)*Supuestos!$C$6:$C$12)+IF(A8>=Supuestos!$F$31,B8*Supuestos!$F$30*Supuestos!$F$29*Supuestos!$F$32,0) -> 5562000 | D8: =IF(B8=0,0,Supuestos!$B$22+(Supuestos!$C$22-Supuestos!$B$22)*(B8-1)/(Supuestos!$F$33-1))-IF(A8>=Supuestos!$B$46,Supuestos!$B$47,0) -> 1181400 | E8: =Supuestos!$C$23*B8/Supuestos!$F$33 -> 866666.67 | F8: =Supuestos!$C$24 -> 100000 | G8: =C8-D8-E8-F8 -> 3413933.3 | H8: =MAX(0,G8)*Supuestos!$B$28 -> 682786.67 | I8: =G8-H8 -> 2731146.7 | J8: =IFERROR(INDEX(Préstamo!$G$18:$G$57,MATCH(A8,Préstamo!$C$18:$C$57,0)),0) -> 1323132.2 | K8: =SUMPRODUCT((Supuestos!$G$6:$G$12<=A8)*(Supuestos!$H$6:$H$12>=A8)*Supuestos!$I$6:$I$12)/Supuestos!$B$43+IF(AND(A8>=Supuestos!$B$46,A8<=EDATE(Supuestos!$B$46,Supuestos!$B$43-1)),Supuestos!$B$45/Supuestos!$B$43,0) -> 3778400 | L8: =I8-J8-K8 -> -2370385.6 | M8: =M7+L8 -> -5182473.9 | N8: =I8-J8 -> 1408014.4 | O8: =O7+N8 -> 3695801.1 | P8: =K8-IF(A8=Supuestos!$F$35,Supuestos!$F$28,0) -> 3778400 | Q8: =Q7+P8 -> 8878275 | R8: =R7+(G8-MAX(0,G8)*Supuestos!$B$29) -> 5646300 | S8: =S7+(G8-MAX(0,G8)*Supuestos!$B$30) -> 5018933.3 | T8: =T7+(G8-MAX(0,G8)*Supuestos!$B$31) -> 4391566.7
A9: =EDATE(A8,1) -> 46388 | B9: =SUMPRODUCT(--(Supuestos!$D$6:$D$12<=A9)) -> 5 | C9: =SUMPRODUCT((Supuestos!$D$6:$D$12<=A9)*Supuestos!$C$6:$C$12)+IF(A9>=Supuestos!$F$31,B9*Supuestos!$F$30*Supuestos!$F$29*Supuestos!$F$32,0) -> 6690000 | D9: =IF(B9=0,0,Supuestos!$B$22+(Supuestos!$C$22-Supuestos!$B$22)*(B9-1)/(Supuestos!$F$33-1))-IF(A9>=Supuestos!$B$46,Supuestos!$B$47,0) -> 1388200 | E9: =Supuestos!$C$23*B9/Supuestos!$F$33 -> 1083333.3 | F9: =Supuestos!$C$24 -> 100000 | G9: =C9-D9-E9-F9 -> 4118466.7 | H9: =MAX(0,G9)*Supuestos!$B$28 -> 823693.33 | I9: =G9-H9 -> 3294773.3 | J9: =IFERROR(INDEX(Préstamo!$G$18:$G$57,MATCH(A9,Préstamo!$C$18:$C$57,0)),0) -> 1323132.2 | K9: =SUMPRODUCT((Supuestos!$G$6:$G$12<=A9)*(Supuestos!$H$6:$H$12>=A9)*Supuestos!$I$6:$I$12)/Supuestos!$B$43+IF(AND(A9>=Supuestos!$B$46,A9<=EDATE(Supuestos!$B$46,Supuestos!$B$43-1)),Supuestos!$B$45/Supuestos!$B$43,0) -> 4597375 | L9: =I9-J9-K9 -> -2625733.9 | M9: =M8+L9 -> -7808207.8 | N9: =I9-J9 -> 1971641.1 | O9: =O8+N9 -> 5667442.2 | P9: =K9-IF(A9=Supuestos!$F$35,Supuestos!$F$28,0) -> 4597375 | Q9: =Q8+P9 -> 13475650 | R9: =R8+(G9-MAX(0,G9)*Supuestos!$B$29) -> 9352920 | S9: =S8+(G9-MAX(0,G9)*Supuestos!$B$30) -> 8313706.7 | T9: =T8+(G9-MAX(0,G9)*Supuestos!$B$31) -> 7274493.3
A10: =EDATE(A9,1) -> 46419 | B10: =SUMPRODUCT(--(Supuestos!$D$6:$D$12<=A10)) -> 6 | C10: =SUMPRODUCT((Supuestos!$D$6:$D$12<=A10)*Supuestos!$C$6:$C$12)+IF(A10>=Supuestos!$F$31,B10*Supuestos!$F$30*Supuestos!$F$29*Supuestos!$F$32,0) -> 7818000 | D10: =IF(B10=0,0,Supuestos!$B$22+(Supuestos!$C$22-Supuestos!$B$22)*(B10-1)/(Supuestos!$F$33-1))-IF(A10>=Supuestos!$B$46,Supuestos!$B$47,0) -> 1595000 | E10: =Supuestos!$C$23*B10/Supuestos!$F$33 -> 1300000 | F10: =Supuestos!$C$24 -> 100000 | G10: =C10-D10-E10-F10 -> 4823000 | H10: =MAX(0,G10)*Supuestos!$B$28 -> 964600 | I10: =G10-H10 -> 3858400 | J10: =IFERROR(INDEX(Préstamo!$G$18:$G$57,MATCH(A10,Préstamo!$C$18:$C$57,0)),0) -> 1323132.2 | K10: =SUMPRODUCT((Supuestos!$G$6:$G$12<=A10)*(Supuestos!$H$6:$H$12>=A10)*Supuestos!$I$6:$I$12)/Supuestos!$B$43+IF(AND(A10>=Supuestos!$B$46,A10<=EDATE(Supuestos!$B$46,Supuestos!$B$43-1)),Supuestos!$B$45/Supuestos!$B$43,0) -> 5416350 | L10: =I10-J10-K10 -> -2881082.2 | M10: =M9+L10 -> -10689290 | N10: =I10-J10 -> 2535267.8 | O10: =O9+N10 -> 8202710 | P10: =K10-IF(A10=Supuestos!$F$35,Supuestos!$F$28,0) -> 5416350 | Q10: =Q9+P10 -> 18892000 | R10: =R9+(G10-MAX(0,G10)*Supuestos!$B$29) -> 13693620 | S10: =S9+(G10-MAX(0,G10)*Supuestos!$B$30) -> 12172107 | T10: =T9+(G10-MAX(0,G10)*Supuestos!$B$31) -> 10650593
A11: =EDATE(A10,1) -> 46447 | B11: =SUMPRODUCT(--(Supuestos!$D$6:$D$12<=A11)) -> 6 | C11: =SUMPRODUCT((Supuestos!$D$6:$D$12<=A11)*Supuestos!$C$6:$C$12)+IF(A11>=Supuestos!$F$31,B11*Supuestos!$F$30*Supuestos!$F$29*Supuestos!$F$32,0) -> 7818000 | D11: =IF(B11=0,0,Supuestos!$B$22+(Supuestos!$C$22-Supuestos!$B$22)*(B11-1)/(Supuestos!$F$33-1))-IF(A11>=Supuestos!$B$46,Supuestos!$B$47,0) -> 1595000 | E11: =Supuestos!$C$23*B11/Supuestos!$F$33 -> 1300000 | F11: =Supuestos!$C$24 -> 100000 | G11: =C11-D11-E11-F11 -> 4823000 | H11: =MAX(0,G11)*Supuestos!$B$28 -> 964600 | I11: =G11-H11 -> 3858400 | J11: =IFERROR(INDEX(Préstamo!$G$18:$G$57,MATCH(A11,Préstamo!$C$18:$C$57,0)),0) -> 1323132.2 | K11: =SUMPRODUCT((Supuestos!$G$6:$G$12<=A11)*(Supuestos!$H$6:$H$12>=A11)*Supuestos!$I$6:$I$12)/Supuestos!$B$43+IF(AND(A11>=Supuestos!$B$46,A11<=EDATE(Supuestos!$B$46,Supuestos!$B$43-1)),Supuestos!$B$45/Supuestos!$B$43,0) -> 5416350 | L11: =I11-J11-K11 -> -2881082.2 | M11: =M10+L11 -> -13570372 | N11: =I11-J11 -> 2535267.8 | O11: =O10+N11 -> 10737978 | P11: =K11-IF(A11=Supuestos!$F$35,Supuestos!$F$28,0) -> 5416350 | Q11: =Q10+P11 -> 24308350 | R11: =R10+(G11-MAX(0,G11)*Supuestos!$B$29) -> 18034320 | S11: =S10+(G11-MAX(0,G11)*Supuestos!$B$30) -> 16030507 | T11: =T10+(G11-MAX(0,G11)*Supuestos!$B$31) -> 14026693
A12: =EDATE(A11,1) -> 46478 | B12: =SUMPRODUCT(--(Supuestos!$D$6:$D$12<=A12)) -> 6 | C12: =SUMPRODUCT((Supuestos!$D$6:$D$12<=A12)*Supuestos!$C$6:$C$12)+IF(A12>=Supuestos!$F$31,B12*Supuestos!$F$30*Supuestos!$F$29*Supuestos!$F$32,0) -> 7818000 | D12: =IF(B12=0,0,Supuestos!$B$22+(Supuestos!$C$22-Supuestos!$B$22)*(B12-1)/(Supuestos!$F$33-1))-IF(A12>=Supuestos!$B$46,Supuestos!$B$47,0) -> 1595000 | E12: =Supuestos!$C$23*B12/Supuestos!$F$33 -> 1300000 | F12: =Supuestos!$C$24 -> 100000 | G12: =C12-D12-E12-F12 -> 4823000 | H12: =MAX(0,G12)*Supuestos!$B$28 -> 964600 | I12: =G12-H12 -> 3858400 | J12: =IFERROR(INDEX(Préstamo!$G$18:$G$57,MATCH(A12,Préstamo!$C$18:$C$57,0)),0) -> 1323132.2 | K12: =SUMPRODUCT((Supuestos!$G$6:$G$12<=A12)*(Supuestos!$H$6:$H$12>=A12)*Supuestos!$I$6:$I$12)/Supuestos!$B$43+IF(AND(A12>=Supuestos!$B$46,A12<=EDATE(Supuestos!$B$46,Supuestos!$B$43-1)),Supuestos!$B$45/Supuestos!$B$43,0) -> 5416350 | L12: =I12-J12-K12 -> -2881082.2 | M12: =M11+L12 -> -16451455 | N12: =I12-J12 -> 2535267.8 | O12: =O11+N12 -> 13273245 | P12: =K12-IF(A12=Supuestos!$F$35,Supuestos!$F$28,0) -> 5416350 | Q12: =Q11+P12 -> 29724700 | R12: =R11+(G12-MAX(0,G12)*Supuestos!$B$29) -> 22375020 | S12: =S11+(G12-MAX(0,G12)*Supuestos!$B$30) -> 19888907 | T12: =T11+(G12-MAX(0,G12)*Supuestos!$B$31) -> 17402793
A13: =EDATE(A12,1) -> 46508 | B13: =SUMPRODUCT(--(Supuestos!$D$6:$D$12<=A13)) -> 6 | C13: =SUMPRODUCT((Supuestos!$D$6:$D$12<=A13)*Supuestos!$C$6:$C$12)+IF(A13>=Supuestos!$F$31,B13*Supuestos!$F$30*Supuestos!$F$29*Supuestos!$F$32,0) -> 7818000 | D13: =IF(B13=0,0,Supuestos!$B$22+(Supuestos!$C$22-Supuestos!$B$22)*(B13-1)/(Supuestos!$F$33-1))-IF(A13>=Supuestos!$B$46,Supuestos!$B$47,0) -> 1595000 | E13: =Supuestos!$C$23*B13/Supuestos!$F$33 -> 1300000 | F13: =Supuestos!$C$24 -> 100000 | G13: =C13-D13-E13-F13 -> 4823000 | H13: =MAX(0,G13)*Supuestos!$B$28 -> 964600 | I13: =G13-H13 -> 3858400 | J13: =IFERROR(INDEX(Préstamo!$G$18:$G$57,MATCH(A13,Préstamo!$C$18:$C$57,0)),0) -> 1323132.2 | K13: =SUMPRODUCT((Supuestos!$G$6:$G$12<=A13)*(Supuestos!$H$6:$H$12>=A13)*Supuestos!$I$6:$I$12)/Supuestos!$B$43+IF(AND(A13>=Supuestos!$B$46,A13<=EDATE(Supuestos!$B$46,Supuestos!$B$43-1)),Supuestos!$B$45/Supuestos!$B$43,0) -> 4597375 | L13: =I13-J13-K13 -> -2062107.2 | M13: =M12+L13 -> -18513562 | N13: =I13-J13 -> 2535267.8 | O13: =O12+N13 -> 15808513 | P13: =K13-IF(A13=Supuestos!$F$35,Supuestos!$F$28,0) -> 4597375 | Q13: =Q12+P13 -> 34322075 | R13: =R12+(G13-MAX(0,G13)*Supuestos!$B$29) -> 26715720 | S13: =S12+(G13-MAX(0,G13)*Supuestos!$B$30) -> 23747307 | T13: =T12+(G13-MAX(0,G13)*Supuestos!$B$31) -> 20778893
A14: =EDATE(A13,1) -> 46539 | B14: =SUMPRODUCT(--(Supuestos!$D$6:$D$12<=A14)) -> 6 | C14: =SUMPRODUCT((Supuestos!$D$6:$D$12<=A14)*Supuestos!$C$6:$C$12)+IF(A14>=Supuestos!$F$31,B14*Supuestos!$F$30*Supuestos!$F$29*Supuestos!$F$32,0) -> 7818000 | D14: =IF(B14=0,0,Supuestos!$B$22+(Supuestos!$C$22-Supuestos!$B$22)*(B14-1)/(Supuestos!$F$33-1))-IF(A14>=Supuestos!$B$46,Supuestos!$B$47,0) -> 1595000 | E14: =Supuestos!$C$23*B14/Supuestos!$F$33 -> 1300000 | F14: =Supuestos!$C$24 -> 100000 | G14: =C14-D14-E14-F14 -> 4823000 | H14: =MAX(0,G14)*Supuestos!$B$28 -> 964600 | I14: =G14-H14 -> 3858400 | J14: =IFERROR(INDEX(Préstamo!$G$18:$G$57,MATCH(A14,Préstamo!$C$18:$C$57,0)),0) -> 1323132.2 | K14: =SUMPRODUCT((Supuestos!$G$6:$G$12<=A14)*(Supuestos!$H$6:$H$12>=A14)*Supuestos!$I$6:$I$12)/Supuestos!$B$43+IF(AND(A14>=Supuestos!$B$46,A14<=EDATE(Supuestos!$B$46,Supuestos!$B$43-1)),Supuestos!$B$45/Supuestos!$B$43,0) -> 3275900 | L14: =I14-J14-K14 -> -740632.24 | M14: =M13+L14 -> -19254194 | N14: =I14-J14 -> 2535267.8 | O14: =O13+N14 -> 18343781 | P14: =K14-IF(A14=Supuestos!$F$35,Supuestos!$F$28,0) -> 3275900 | Q14: =Q13+P14 -> 37597975 | R14: =R13+(G14-MAX(0,G14)*Supuestos!$B$29) -> 31056420 | S14: =S13+(G14-MAX(0,G14)*Supuestos!$B$30) -> 27605707 | T14: =T13+(G14-MAX(0,G14)*Supuestos!$B$31) -> 24154993
A15: =EDATE(A14,1) -> 46569 | B15: =SUMPRODUCT(--(Supuestos!$D$6:$D$12<=A15)) -> 6 | C15: =SUMPRODUCT((Supuestos!$D$6:$D$12<=A15)*Supuestos!$C$6:$C$12)+IF(A15>=Supuestos!$F$31,B15*Supuestos!$F$30*Supuestos!$F$29*Supuestos!$F$32,0) -> 7818000 | D15: =IF(B15=0,0,Supuestos!$B$22+(Supuestos!$C$22-Supuestos!$B$22)*(B15-1)/(Supuestos!$F$33-1))-IF(A15>=Supuestos!$B$46,Supuestos!$B$47,0) -> 1595000 | E15: =Supuestos!$C$23*B15/Supuestos!$F$33 -> 1300000 | F15: =Supuestos!$C$24 -> 100000 | G15: =C15-D15-E15-F15 -> 4823000 | H15: =MAX(0,G15)*Supuestos!$B$28 -> 964600 | I15: =G15-H15 -> 3858400 | J15: =IFERROR(INDEX(Préstamo!$G$18:$G$57,MATCH(A15,Préstamo!$C$18:$C$57,0)),0) -> 1323132.2 | K15: =SUMPRODUCT((Supuestos!$G$6:$G$12<=A15)*(Supuestos!$H$6:$H$12>=A15)*Supuestos!$I$6:$I$12)/Supuestos!$B$43+IF(AND(A15>=Supuestos!$B$46,A15<=EDATE(Supuestos!$B$46,Supuestos!$B$43-1)),Supuestos!$B$45/Supuestos!$B$43,0) -> 2456925 | L15: =I15-J15-K15 -> 78342.762 | M15: =M14+L15 -> -19175851 | N15: =I15-J15 -> 2535267.8 | O15: =O14+N15 -> 20879049 | P15: =K15-IF(A15=Supuestos!$F$35,Supuestos!$F$28,0) -> 2456925 | Q15: =Q14+P15 -> 40054900 | R15: =R14+(G15-MAX(0,G15)*Supuestos!$B$29) -> 35397120 | S15: =S14+(G15-MAX(0,G15)*Supuestos!$B$30) -> 31464107 | T15: =T14+(G15-MAX(0,G15)*Supuestos!$B$31) -> 27531093
A16: =EDATE(A15,1) -> 46600 | B16: =SUMPRODUCT(--(Supuestos!$D$6:$D$12<=A16)) -> 6 | C16: =SUMPRODUCT((Supuestos!$D$6:$D$12<=A16)*Supuestos!$C$6:$C$12)+IF(A16>=Supuestos!$F$31,B16*Supuestos!$F$30*Supuestos!$F$29*Supuestos!$F$32,0) -> 7818000 | D16: =IF(B16=0,0,Supuestos!$B$22+(Supuestos!$C$22-Supuestos!$B$22)*(B16-1)/(Supuestos!$F$33-1))-IF(A16>=Supuestos!$B$46,Supuestos!$B$47,0) -> 1595000 | E16: =Supuestos!$C$23*B16/Supuestos!$F$33 -> 1300000 | F16: =Supuestos!$C$24 -> 100000 | G16: =C16-D16-E16-F16 -> 4823000 | H16: =MAX(0,G16)*Supuestos!$B$28 -> 964600 | I16: =G16-H16 -> 3858400 | J16: =IFERROR(INDEX(Préstamo!$G$18:$G$57,MATCH(A16,Préstamo!$C$18:$C$57,0)),0) -> 1323132.2 | K16: =SUMPRODUCT((Supuestos!$G$6:$G$12<=A16)*(Supuestos!$H$6:$H$12>=A16)*Supuestos!$I$6:$I$12)/Supuestos!$B$43+IF(AND(A16>=Supuestos!$B$46,A16<=EDATE(Supuestos!$B$46,Supuestos!$B$43-1)),Supuestos!$B$45/Supuestos!$B$43,0) -> 1637950 | L16: =I16-J16-K16 -> 897317.76 | M16: =M15+L16 -> -18278533 | N16: =I16-J16 -> 2535267.8 | O16: =O15+N16 -> 23414317 | P16: =K16-IF(A16=Supuestos!$F$35,Supuestos!$F$28,0) -> 1637950 | Q16: =Q15+P16 -> 41692850 | R16: =R15+(G16-MAX(0,G16)*Supuestos!$B$29) -> 39737820 | S16: =S15+(G16-MAX(0,G16)*Supuestos!$B$30) -> 35322507 | T16: =T15+(G16-MAX(0,G16)*Supuestos!$B$31) -> 30907193
A17: =EDATE(A16,1) -> 46631 | B17: =SUMPRODUCT(--(Supuestos!$D$6:$D$12<=A17)) -> 6 | C17: =SUMPRODUCT((Supuestos!$D$6:$D$12<=A17)*Supuestos!$C$6:$C$12)+IF(A17>=Supuestos!$F$31,B17*Supuestos!$F$30*Supuestos!$F$29*Supuestos!$F$32,0) -> 7818000 | D17: =IF(B17=0,0,Supuestos!$B$22+(Supuestos!$C$22-Supuestos!$B$22)*(B17-1)/(Supuestos!$F$33-1))-IF(A17>=Supuestos!$B$46,Supuestos!$B$47,0) -> 1595000 | E17: =Supuestos!$C$23*B17/Supuestos!$F$33 -> 1300000 | F17: =Supuestos!$C$24 -> 100000 | G17: =C17-D17-E17-F17 -> 4823000 | H17: =MAX(0,G17)*Supuestos!$B$28 -> 964600 | I17: =G17-H17 -> 3858400 | J17: =IFERROR(INDEX(Préstamo!$G$18:$G$57,MATCH(A17,Préstamo!$C$18:$C$57,0)),0) -> 1323132.2 | K17: =SUMPRODUCT((Supuestos!$G$6:$G$12<=A17)*(Supuestos!$H$6:$H$12>=A17)*Supuestos!$I$6:$I$12)/Supuestos!$B$43+IF(AND(A17>=Supuestos!$B$46,A17<=EDATE(Supuestos!$B$46,Supuestos!$B$43-1)),Supuestos!$B$45/Supuestos!$B$43,0) -> 818975 | L17: =I17-J17-K17 -> 1716292.8 | M17: =M16+L17 -> -16562241 | N17: =I17-J17 -> 2535267.8 | O17: =O16+N17 -> 25949584 | P17: =K17-IF(A17=Supuestos!$F$35,Supuestos!$F$28,0) -> 818975 | Q17: =Q16+P17 -> 42511825 | R17: =R16+(G17-MAX(0,G17)*Supuestos!$B$29) -> 44078520 | S17: =S16+(G17-MAX(0,G17)*Supuestos!$B$30) -> 39180907 | T17: =T16+(G17-MAX(0,G17)*Supuestos!$B$31) -> 34283293
A18: =EDATE(A17,1) -> 46661 | B18: =SUMPRODUCT(--(Supuestos!$D$6:$D$12<=A18)) -> 6 | C18: =SUMPRODUCT((Supuestos!$D$6:$D$12<=A18)*Supuestos!$C$6:$C$12)+IF(A18>=Supuestos!$F$31,B18*Supuestos!$F$30*Supuestos!$F$29*Supuestos!$F$32,0) -> 7818000 | D18: =IF(B18=0,0,Supuestos!$B$22+(Supuestos!$C$22-Supuestos!$B$22)*(B18-1)/(Supuestos!$F$33-1))-IF(A18>=Supuestos!$B$46,Supuestos!$B$47,0) -> 1595000 | E18: =Supuestos!$C$23*B18/Supuestos!$F$33 -> 1300000 | F18: =Supuestos!$C$24 -> 100000 | G18: =C18-D18-E18-F18 -> 4823000 | H18: =MAX(0,G18)*Supuestos!$B$28 -> 964600 | I18: =G18-H18 -> 3858400 | J18: =IFERROR(INDEX(Préstamo!$G$18:$G$57,MATCH(A18,Préstamo!$C$18:$C$57,0)),0) -> 1323132.2 | K18: =SUMPRODUCT((Supuestos!$G$6:$G$12<=A18)*(Supuestos!$H$6:$H$12>=A18)*Supuestos!$I$6:$I$12)/Supuestos!$B$43+IF(AND(A18>=Supuestos!$B$46,A18<=EDATE(Supuestos!$B$46,Supuestos!$B$43-1)),Supuestos!$B$45/Supuestos!$B$43,0) -> 0 | L18: =I18-J18-K18 -> 2535267.8 | M18: =M17+L18 -> -14026973 | N18: =I18-J18 -> 2535267.8 | O18: =O17+N18 -> 28484852 | P18: =K18-IF(A18=Supuestos!$F$35,Supuestos!$F$28,0) -> 0 | Q18: =Q17+P18 -> 42511825 | R18: =R17+(G18-MAX(0,G18)*Supuestos!$B$29) -> 48419220 | S18: =S17+(G18-MAX(0,G18)*Supuestos!$B$30) -> 43039307 | T18: =T17+(G18-MAX(0,G18)*Supuestos!$B$31) -> 37659393
... A77: =EDATE(A76,1) -> 48458 | B77: =SUMPRODUCT(--(Supuestos!$D$6:$D$12<=A77)) -> 7 | C77: =SUMPRODUCT((Supuestos!$D$6:$D$12<=A77)*Supuestos!$C$6:$C$12)+IF(A77>=Supuestos!$F$31,B77*Supuestos!$F$30*Supuestos!$F$29*Supuestos!$F$32,0) -> 9246000 | D77: =IF(B77=0,0,Supuestos!$B$22+(Supuestos!$C$22-Supuestos!$B$22)*(B77-1)/(Supuestos!$F$33-1))-IF(A77>=Supuestos!$B$46,Supuestos!$B$47,0) -> 1801800 | E77: =Supuestos!$C$23*B77/Supuestos!$F$33 -> 1516666.7 | F77: =Supuestos!$C$24 -> 100000 | G77: =C77-D77-E77-F77 -> 5827533.3 | H77: =MAX(0,G77)*Supuestos!$B$28 -> 1165506.7 | I77: =G77-H77 -> 4662026.7 | J77: =IFERROR(INDEX(Préstamo!$G$18:$G$57,MATCH(A77,Préstamo!$C$18:$C$57,0)),0) -> 0 | K77: =SUMPRODUCT((Supuestos!$G$6:$G$12<=A77)*(Supuestos!$H$6:$H$12>=A77)*Supuestos!$I$6:$I$12)/Supuestos!$B$43+IF(AND(A77>=Supuestos!$B$46,A77<=EDATE(Supuestos!$B$46,Supuestos!$B$43-1)),Supuestos!$B$45/Supuestos!$B$43,0) -> 0 | L77: =I77-J77-K77 -> 4662026.7 | M77: =M76+L77 -> 2.1738436e+08 | N77: =I77-J77 -> 4662026.7 | O77: =O76+N77 -> 2.6644799e+08 | P77: =K77-IF(A77=Supuestos!$F$35,Supuestos!$F$28,0) -> 0 | Q77: =Q76+P77 -> 49063625 | R77: =R76+(G77-MAX(0,G77)*Supuestos!$B$29) -> 353340840 | S77: =S76+(G77-MAX(0,G77)*Supuestos!$B$30) -> 3.1408075e+08 | T77: =T76+(G77-MAX(0,G77)*Supuestos!$B$31) -> 2.7482065e+08

Sheet Escenarios
A1: Escenarios de comisión y tiempo de recuperación
A2: Casa completa con 7 habitaciones arrendadas y lavandería con monedero. La comisión de administración se calcula sobre el ingreso neto operativo (después de gastos).
A4: 1. Inversión total a recuperar
A5: Obra y adecuaciones (incluye pendientes, bomba y 4x1000) | B5: =SUMIFS(Movimientos!$I$6:$I$205,Movimientos!$M$6:$M$205,"Obra y adecuaciones",Movimientos!$L$6:$L$205,"Gasto") -> 124705973
A6: Mobiliario 7 habitaciones (real + estimado) | B6: =Supuestos!$I$13 -> 45862600
A7: Lavandería (lavadora + monedero) | B7: =Supuestos!$B$45 -> 4020000
A8: Subtotal capital invertido (menos venta de objetos almacenados) | B8: =SUM(B5:B7)-Supuestos!$F$28 -> 174588573
A9: Intereses préstamo mamá (36 cuotas) | B9: =Préstamo!$B$13 -> 12632761
A10: INVERSIÓN TOTAL A RECUPERAR | B10: =B8+B9 -> 1.8722133e+08
A14: 2. Casa completa: 7 habitaciones + lavandería (estabilizado)
A15: Concepto | B15: =Supuestos!$B$29 -> 0.1 | C15: =Supuestos!$B$30 -> 0.2 | D15: =Supuestos!$B$31 -> 0.3
A16: Ingreso bruto mensual (arriendos + lavandería) | B16: =Supuestos!$C$13+Supuestos!$F$30*Supuestos!$F$29*Supuestos!$F$32*COUNTA(Supuestos!$A$6:$A$12) -> 9246000 | C16: =Supuestos!$C$13+Supuestos!$F$30*Supuestos!$F$29*Supuestos!$F$32*COUNTA(Supuestos!$A$6:$A$12) -> 9246000 | D16: =Supuestos!$C$13+Supuestos!$F$30*Supuestos!$F$29*Supuestos!$F$32*COUNTA(Supuestos!$A$6:$A$12) -> 9246000
A17: Gastos de operación (extrapolados a 7 inquilinos, con ahorro de la lavadora) | B17: =-(Supuestos!$B$22+(Supuestos!$C$22-Supuestos!$B$22)*(COUNTA(Supuestos!$A$6:$A$12)-1)/(Supuestos!$F$33-1)+Supuestos!$C$23*COUNTA(Supuestos!$A$6:$A$12)/Supuestos!$F$33+Supuestos!$C$24-Supuestos!$B$47) -> -3418466.7 | C17: =-(Supuestos!$B$22+(Supuestos!$C$22-Supuestos!$B$22)*(COUNTA(Supuestos!$A$6:$A$12)-1)/(Supuestos!$F$33-1)+Supuestos!$C$23*COUNTA(Supuestos!$A$6:$A$12)/Supuestos!$F$33+Supuestos!$C$24-Supuestos!$B$47) -> -3418466.7 | D17: =-(Supuestos!$B$22+(Supuestos!$C$22-Supuestos!$B$22)*(COUNTA(Supuestos!$A$6:$A$12)-1)/(Supuestos!$F$33-1)+Supuestos!$C$23*COUNTA(Supuestos!$A$6:$A$12)/Supuestos!$F$33+Supuestos!$C$24-Supuestos!$B$47) -> -3418466.7
A18: Neto operativo | B18: =B16+B17 -> 5827533.3 | C18: =C16+C17 -> 5827533.3 | D18: =D16+D17 -> 5827533.3
A19: Comisión de administración | B19: =-MAX(0,B18)*Supuestos!$B$29 -> -582753.33 | C19: =-MAX(0,C18)*Supuestos!$B$30 -> -1165506.7 | D19: =-MAX(0,D18)*Supuestos!$B$31 -> -1748260
A20: Neto casa para los abuelos (antes de deudas) | B20: =B18+B19 -> 5244780 | C20: =C18+C19 -> 4662026.7 | D20: =D18+D19 -> 4079273.3
A21: Cuota préstamo mamá (dic 2026 – nov 2029) | B21: =-Préstamo!$B$11 -> -1323132.2 | C21: =-Préstamo!$B$11 -> -1323132.2 | D21: =-Préstamo!$B$11 -> -1323132.2
A22: Neto para los abuelos mientras se paga el préstamo | B22: =B20+B21 -> 3921647.8 | C22: =C20+C21 -> 3338894.4 | D22: =D20+D21 -> 2756141.1
A23: Neto anual (antes de deudas) | B23: =B20*12 -> 62937360 | C23: =C20*12 -> 55944320 | D23: =D20*12 -> 48951280
A24: Rentabilidad anual sobre la inversión total | B24: =IFERROR(B23/$B$10,0) -> 0.33616554 | C24: =IFERROR(C23/$B$10,0) -> 0.29881381 | D24: =IFERROR(D23/$B$10,0) -> 0.26146208
A25: Recuperación simple, como si la casa estuviera llena desde el día 1 (años) | B25: =IFERROR($B$10/B23,0) -> 2.9747249 | C25: =IFERROR($B$10/C23,0) -> 3.3465655 | D25: =IFERROR($B$10/D23,0) -> 3.8246463
A26: Recuperación con llenado gradual (meses desde oct 2026) | B26: =IF(COUNTIF('Flujo Proyectado'!$R$6:$R$77,"<"&$B$10)>=72,"más de 72",COUNTIF('Flujo Proyectado'!$R$6:$R$77,"<"&$B$10)+1) -> 41 | C26: =IF(COUNTIF('Flujo Proyectado'!$S$6:$S$77,"<"&$B$10)>=72,"más de 72",COUNTIF('Flujo Proyectado'!$S$6:$S$77,"<"&$B$10)+1) -> 45 | D26: =IF(COUNTIF('Flujo Proyectado'!$T$6:$T$77,"<"&$B$10)>=72,"más de 72",COUNTIF('Flujo Proyectado'!$T$6:$T$77,"<"&$B$10)+1) -> 51
A27: Mes en que se recupera toda la inversión | B27: =IF(ISNUMBER(B26),EDATE(Supuestos!$B$54,B26-1),"—") -> 47515 | C27: =IF(ISNUMBER(C26),EDATE(Supuestos!$B$54,C26-1),"—") -> 47635 | D27: =IF(ISNUMBER(D26),EDATE(Supuestos!$B$54,D26-1),"—") -> 47818
A28: Ganancia adicional vs. antes de la remodelación (mensual) | B28: =B20-Supuestos!$B$50 -> 4624780 | C28: =C20-Supuestos!$B$50 -> 4042026.7 | D28: =D20-Supuestos!$B$50 -> 3459273.3
A29: Ingreso mensual de Felipe por administración | B29: =-B19 -> 582753.33 | C29: =-C19 -> 1165506.7 | D29: =-D19 -> 1748260
A32: 3. Referencia de mercado para la comisión
A33: Honorario inmobiliaria tradicional: % sobre canon bruto + IVA | B33: =Supuestos!$B$52*(1+Supuestos!$B$53) -> 0.119
A34: Equivale en pesos a (mensual, casa completa) | B34: =B33*B16 -> 1100274
A35: Equivale como % del ingreso neto operativo | B35: =IFERROR(B34/B18,0) -> 0.18880613
A36: Una inmobiliaria administra 1 contrato por inmueble. Aquí son 7 contratos, servicios compartidos, rotación de inquilinos, aseo y mantenimiento de un coliving: más carga que una administración tradicional, y la inmobiliaria además suele cobrar un canon por cada inquilino nuevo.
A40: Fuente referencia: Inmobiliare Latam, 'Administración de inmuebles en Bogotá: guía 2026' (8%–12% del canon + IVA).
A42: 4. Mientras la habitación 7 sigue de bodega (6 habitaciones + lavandería)
A43: Concepto | B43: =Supuestos!$B$29 -> 0.1 | C43: =Supuestos!$B$30 -> 0.2 | D43: =Supuestos!$B$31 -> 0.3
A44: Ingreso bruto mensual (arriendos + lavandería) | B44: =SUM(Supuestos!$C$6:$C$11)+Supuestos!$F$30*Supuestos!$F$29*Supuestos!$F$32*6 -> 7818000 | C44: =SUM(Supuestos!$C$6:$C$11)+Supuestos!$F$30*Supuestos!$F$29*Supuestos!$F$32*6 -> 7818000 | D44: =SUM(Supuestos!$C$6:$C$11)+Supuestos!$F$30*Supuestos!$F$29*Supuestos!$F$32*6 -> 7818000
A45: Gastos de operación (con ahorro de la lavadora) | B45: =-(Supuestos!$C$25-Supuestos!$B$47) -> -2995000 | C45: =-(Supuestos!$C$25-Supuestos!$B$47) -> -2995000 | D45: =-(Supuestos!$C$25-Supuestos!$B$47) -> -2995000
A46: Neto operativo | B46: =B44+B45 -> 4823000 | C46: =C44+C45 -> 4823000 | D46: =D44+D45 -> 4823000
A47: Comisión de administración | B47: =-MAX(0,B46)*Supuestos!$B$29 -> -482300 | C47: =-MAX(0,C46)*Supuestos!$B$30 -> -964600 | D47: =-MAX(0,D46)*Supuestos!$B$31 -> -1446900
A48: Neto casa para los abuelos (antes de deudas) | B48: =B46+B47 -> 4340700 | C48: =C46+C47 -> 3858400 | D48: =D46+D47 -> 3376100
A49: Cuota préstamo mamá | B49: =-Préstamo!$B$11 -> -1323132.2 | C49: =-Préstamo!$B$11 -> -1323132.2 | D49: =-Préstamo!$B$11 -> -1323132.2
A50: Neto para los abuelos mientras se paga el préstamo | B50: =B48+B49 -> 3017567.8 | C50: =C48+C49 -> 2535267.8 | D50: =D48+D49 -> 2052967.8

Sheet Comparación
A1: Comparación: la casa frente a otras alternativas
A2: Rentabilidades antes de impuestos. Los CDT y la cuenta de ahorros tienen retención en la fuente; la casa ya descuenta predial y reservas.
A4: 1. ¿Cuánto rinde el mismo dinero en cada alternativa? (capital = inversión total)
A5: Alternativa | B5: Rentabilidad anual | C5: Ingreso anual | D5: Ingreso mensual promedio
A6: Cuenta de ahorros actual de los abuelos | B6: =Supuestos!$B$38 -> 0.085 | C6: =B6*Escenarios!$B$10 -> 15913813 | D6: =C6/12 -> 1326151.1
A7: CDT 360 días — promedio del mercado (sep 2026) | B7: =Supuestos!$B$40 -> 0.1207 | C7: =B7*Escenarios!$B$10 -> 22597615 | D7: =C7/12 -> 1883134.6
A8: CDT 360 días — mejor tasa del mercado (sep 2026) | B8: =Supuestos!$B$41 -> 0.13 | C8: =B8*Escenarios!$B$10 -> 24338773 | D8: =C8/12 -> 2028231.1
A9: La Clarita — comisión 10% | B9: =Escenarios!$B$24 -> 0.33616554 | C9: =B9*Escenarios!$B$10 -> 62937360 | D9: =C9/12 -> 5244780
A10: La Clarita — comisión 20% | B10: =Escenarios!$C$24 -> 0.29881381 | C10: =B10*Escenarios!$B$10 -> 55944320 | D10: =C10/12 -> 4662026.7
A11: La Clarita — comisión 30% | B11: =Escenarios!$D$24 -> 0.26146208 | C11: =B11*Escenarios!$B$10 -> 48951280 | D11: =C11/12 -> 4079273.3
A12: La casa rinde más, pero exige administración, tiene riesgo de vacancia y el capital queda en el inmueble (no se puede retirar como un CDT). A cambio, la casa conserva su valor como propiedad.
A15: 2. Opción A vs. Opción B — ¿de qué caja salen los muebles?
A16: Concepto | B16: A 6 meses | C16: A 12 meses | D16: A 24 meses
A17: Fecha de corte | B17: =EDATE(Supuestos!$B$54,5) -> 46447 | C17: =EDATE(Supuestos!$B$54,11) -> 46631 | D17: =EDATE(Supuestos!$B$54,23) -> 46997
A18: Caja de la casa acumulada — Opción A (arriendo paga muebles) | B18: =INDEX('Flujo Proyectado'!$M$6:$M$77,MATCH(B$17,'Flujo Proyectado'!$A$6:$A$77,0)) -> -13570372 | C18: =INDEX('Flujo Proyectado'!$M$6:$M$77,MATCH(C$17,'Flujo Proyectado'!$A$6:$A$77,0)) -> -16562241 | D18: =INDEX('Flujo Proyectado'!$M$6:$M$77,MATCH(D$17,'Flujo Proyectado'!$A$6:$A$77,0)) -> 13768882
A19: Caja de la casa acumulada — Opción B (ahorros pagan muebles) | B19: =INDEX('Flujo Proyectado'!$O$6:$O$77,MATCH(B$17,'Flujo Proyectado'!$A$6:$A$77,0)) -> 10737978 | C19: =INDEX('Flujo Proyectado'!$O$6:$O$77,MATCH(C$17,'Flujo Proyectado'!$A$6:$A$77,0)) -> 25949584 | D19: =INDEX('Flujo Proyectado'!$O$6:$O$77,MATCH(D$17,'Flujo Proyectado'!$A$6:$A$77,0)) -> 61194557
A20: Dinero tomado de los ahorros para muebles y lavadora — Opción B | B20: =INDEX('Flujo Proyectado'!$Q$6:$Q$77,MATCH(B$17,'Flujo Proyectado'!$A$6:$A$77,0)) -> 24308350 | C20: =INDEX('Flujo Proyectado'!$Q$6:$Q$77,MATCH(C$17,'Flujo Proyectado'!$A$6:$A$77,0)) -> 42511825 | D20: =INDEX('Flujo Proyectado'!$Q$6:$Q$77,MATCH(D$17,'Flujo Proyectado'!$A$6:$A$77,0)) -> 47425675
A21: Saldo ILUSTRATIVO de ahorros después de pagar los muebles (sin contar intereses) | B21: =Supuestos!$B$39-B20 -> 75691650 | C21: =Supuestos!$B$39-C20 -> 57488175 | D21: =Supuestos!$B$39-D20 -> 52574325
A22: En las dos opciones los abuelos terminan con prácticamente el mismo patrimonio: los muebles se pagan con la misma plata. La diferencia es que en la Opción A la casa no alcanza a cubrir sus obligaciones mes a mes y alguien tiene que tapar el hueco.
A25: 3. Señales de la Opción A (el arriendo paga préstamo + muebles)
A26: Meses con caja negativa en los primeros 12 meses | B26: =COUNTIF('Flujo Proyectado'!$L$6:$L$17,"<0") -> 9
A27: Peor momento de la caja acumulada (primeros 24 meses) | B27: =MIN('Flujo Proyectado'!$M$6:$M$29) -> -19254194
A28: Resultado de caja del mes más difícil | B28: =MIN('Flujo Proyectado'!$L$6:$L$29) -> -2881082.2
A29: Ese faltante no tiene fuente: si no sale de los ahorros, se deja de pagar la cuota a mamá o la tarjeta, y no queda ganancia para nadie.
A32: 4. Si el efectivo se guarda para otra propiedad
A33: Rendimiento extra al año por cada $10.000.000 que pasen de la cuenta (8,5%) a un CDT promedio | B33: =10000000*(Supuestos!$B$40-Supuestos!$B$38) -> 357000
A34: Fuentes: Infobae (29 sep 2026) y El País (sep 2026) — promedio CDT 360 días 12,07% EA según Banco de la República; finanzasplus.co — tasas hasta 13% EA.

Sheet Valoración
A1: ¿Cuánto podría valer la casa para un inversionista?
A2: Estimación de referencia por dos métodos. Antes de publicar un precio: avalúo comercial profesional (Lonja o perito RAA).
A4: Datos del inmueble
A5: Barrio / localidad | B5: La Clarita, Engativá — Bogotá
A6: Estrato | B6: 3
A7: Frente del lote (m) | B7: 6
A8: Fondo del lote (m) | B8: 12
A9: Área del lote (m²) | B9: =B7*B8 -> 72
A10: Área construida (m²) | B10: 190
A11: Pisos | B11: 3 + terraza
A12: Habitaciones de renta | B12: =COUNTA(Supuestos!$A$6:$A$12) -> 7
A14: Método 1 — Comparables en venta en La Clarita (precios de oferta)
A15: Inmueble | B15: Área construida (m²) | C15: Precio de oferta | D15: Precio por m²
A16: Casa 4 hab / 3 baños | B16: 155 | C16: 450000000 | D16: =C16/B16 -> 2903225.8
A17: Casa 4 hab / 2 baños | B17: 120 | C17: 550000000 | D17: =C17/B17 -> 4583333.3
A18: Casa 4 hab / 2 baños | B18: 242 | C18: 580000000 | D18: =C18/B18 -> 2396694.2
A19: Casa 3 hab / 3 baños | B19: 160 | C19: 640000000 | D19: =C19/B19 -> 4000000
A20: Promedio comparables | D20: =AVERAGE(D16:D19) -> 3470813.3
A21: Promedio Engativá (casas, precio por m²) | D21: 3412157
A22: Descuento de negociación sobre precio de oferta | D22: 0.07
A23: Valor por comparables (promedio La Clarita, con descuento) | D23: =B10*D20*(1-D22) -> 6.1329272e+08
A24: Valor por comparables (promedio Engativá, con descuento) | D24: =B10*D21*(1-D22) -> 6.0292814e+08
A25: Fuentes: listados en Fincaraíz / Properati / Mercado Libre para La Clarita, y Habi.co ('Valor del metro cuadrado en Bogotá por localidad'), consultados 30 sep 2026. Son precios de oferta, no de cierre. Los comparables no están remodelados para renta.
A28: Método 2 — Por la renta que produce (lo que mira un inversionista) | B28: Casa completa (7 hab) | C28: Hoy (6 hab)
A29: Ingreso neto operativo anual estabilizado (arriendos + lavandería − gastos) | B29: =(Escenarios!$B$18)*12 -> 69930400 | C29: =(Escenarios!$B$46)*12 -> 57876000
A30: Menos administración a precio de mercado (el comprador tendría que pagarla) | B30: =-Escenarios!$B$34*12 -> -13203288 | C30: =-Escenarios!$B$33*Escenarios!$B$44*12 -> -11164104
A31: Ingreso neto anual para un inversionista | B31: =B29+B30 -> 56727112 | C31: =C29+C30 -> 46711896
A32: Equivale a un flujo de caja mensual de | B32: =B31/12 -> 4727259.3 | C32: =C31/12 -> 3892658
A33: Tasa de capitalización exigida | B33: Valor — casa completa | C33: Valor — hoy (6 hab) | D33: Lectura
A34: 0.07 | B34: =B$31/A34 -> 8.1038731e+08 | C34: =C$31/A34 -> 667312800 | D34: Inversionista que valora la renta ya probada
A35: 0.08 | B35: =B$31/A35 -> 709088900 | C35: =C$31/A35 -> 583898700 | D35: Punto medio
A36: 0.09 | B36: =B$31/A36 -> 6.3030124e+08 | C36: =C$31/A36 -> 5.1902107e+08 | D36: Inversionista que castiga el riesgo del coliving
A37: Tasa de capitalización = ingreso neto anual ÷ precio. Supuesto de Felipe/Claude, no dato de mercado: para vivienda por habitaciones con 7 contratos se exige más que para un arriendo tradicional. La venta se entrega amoblada y con contratos vigentes.
A40: Rango de referencia
A41: Valor mínimo de los métodos | B41: =MIN(D23,D24,B34,B35,B36) -> 6.0292814e+08
A42: Valor máximo de los métodos | B42: =MAX(D23,D24,B34,B35,B36) -> 8.1038731e+08
A43: Punto medio | B43: =AVERAGE(B41,B42) -> 7.0665773e+08
A45: Qué revisaría un comprador: (0) un comprador paga por ingreso con historial, no por ingreso proyectado — la Hab 7 y el monedero aún no existen, y el Registro Mensual es la evidencia que respalda el valor por renta; (1) el ingreso depende de que alguien administre las 7 habitaciones; (2) la casa es una sola unidad, sin independización; (3) la obra fue interna sin licencia — conviene confirmar con un curador o abogado que las adecuaciones (baños y cocinas nuevas) no la requerían; (4) contratos vigentes y su historial de pago.

Sheet Supuestos
A1: Supuestos y parámetros
A2: Azul = dato ingresado · Negro = fórmula · Verde = viene de otra hoja · Amarillo = POR CONFIRMAR. Cambie aquí y todo el libro se recalcula.
A4: Habitaciones
A5: Habitación | B5: Tipo | C5: Canon mensual | D5: Fecha ingreso inquilino | E5: Estado | F5: Fecha compra mobiliario | G5: Mes 1ª cuota muebles | H5: Mes última cuota | I5: Costo amoblado
A6: Hab 1 | B6: Grande | C6: 1250000 | D6: 46280 | E6: Contrato firmado — inicio 15 sep 2026 | F6: 46266 | G6: =DATE(YEAR(F6),MONTH(F6),1) -> 46266 | H6: =EDATE(G6,$B$43-1) -> 46478 | I6: =Mobiliario!B44 -> 6551800
A7: Hab 2 | B7: Grande | C7: 1500000 | D7: 46310 | E7: Interesado aceptó precio — reuniendo documentos | F7: 46310 | G7: =DATE(YEAR(F7),MONTH(F7),1) -> 46296 | H7: =EDATE(G7,$B$43-1) -> 46508 | I7: =Mobiliario!C44 -> 6551800
A8: Hab 3 | B8: Grande | C8: 1350000 | D8: 46327 | E8: Proyectado (precio mínimo esperado) | F8: 46327 | G8: =DATE(YEAR(F8),MONTH(F8),1) -> 46327 | H8: =EDATE(G8,$B$43-1) -> 46539 | I8: =Mobiliario!D44 -> 6551800
A9: Hab 4 | B9: Grande | C9: 1350000 | D9: 46357 | E9: Proyectado (precio mínimo esperado) | F9: 46357 | G9: =DATE(YEAR(F9),MONTH(F9),1) -> 46357 | H9: =EDATE(G9,$B$43-1) -> 46569 | I9: =Mobiliario!E44 -> 6551800
A10: Hab 5 | B10: Pequeña | C10: 1100000 | D10: 46388 | E10: Proyectado | F10: 46388 | G10: =DATE(YEAR(F10),MONTH(F10),1) -> 46388 | H10: =EDATE(G10,$B$43-1) -> 46600 | I10: =Mobiliario!F44 -> 6551800
A11: Hab 6 | B11: Pequeña | C11: 1100000 | D11: 46419 | E11: Proyectado | F11: 46419 | G11: =DATE(YEAR(F11),MONTH(F11),1) -> 46419 | H11: =EDATE(G11,$B$43-1) -> 46631 | I11: =Mobiliario!G44 -> 6551800
A12: Hab 7 | B12: Grande | C12: 1400000 | D12: 46844 | E12: Hoy es bodega de objetos de los abuelos — disponible en 1–2 años | F12: 46844 | G12: =DATE(YEAR(F12),MONTH(F12),1) -> 46844 | H12: =EDATE(G12,$B$43-1) -> 47058 | I12: =Mobiliario!H44 -> 6551800
A13: Total 7 habitaciones | C13: =SUM(C6:C12) -> 9050000 | I13: =SUM(I6:I12) -> 45862600
A14: Habitaciones 3 a 7: precios esperados por Felipe. Ritmo base: 1 habitación nueva por mes hasta la 6. La 7 se habilita cuando salgan los objetos almacenados (se trasladan o se venden).
A15: Gastos mensuales de operación
A16: Concepto | B16: Actual (1 inquilino) | C16: Estimado (6 inquilinos) | D16: Nota
A17: Energía | B17: 170000 | C17: 600000 | D17: 7 duchas eléctricas a 220V: el rubro más sensible
A18: Gas | B18: 46000 | C18: 120000
A19: Acueducto | B19: 80000 | C19: 220000
A20: Internet | B20: 200000 | C20: 200000
A21: Aseo | B21: 110000 | C21: 500000 | D21: Persona de aseo semanal — valor mensual acordado
A22: Subtotal servicios | B22: =SUM(B17:B21) -> 606000 | C22: =SUM(C17:C21) -> 1640000
A23: Reserva reparaciones menores/mayores + vacancia | B23: 0 | C23: 1300000 | D23: Se provisiona en proporción a las habitaciones ocupadas
A24: Ahorro mensual impuesto predial | B24: 100000 | C24: 100000
A25: Total gastos de operación | B25: =B22+B23+B24 -> 706000 | C25: =C22+C23+C24 -> 3040000 | D25: Fuente: estimados de Felipe (sep 2026). Sin la comisión de administración.
A27: Parámetros financieros | E27: Habitación 7, lavandería y muebles
A28: Comisión de administración seleccionada (sobre ingreso neto operativo) | B28: 0.2 | C28: Cambie a 10%, 20% o 30% para ver cada escenario en todo el libro | E28: Hab 7 — venta de objetos almacenados (ingreso único) | F28: 0 | G28: Valor desconocido, probablemente < $10M. Se deja en 0 (conservador)
A29: Escenario comisión 1 | B29: 0.1 | E29: Monedero — precio por ciclo de lavado | F29: 7000 | G29: Definido por Felipe. El contrato ya contempla cobro por ciclo (gratis hasta instalar el monedero)
A30: Escenario comisión 2 | B30: 0.2 | E30: Ciclos de lavado por inquilino al mes | F30: 4 | G30: Supuesto: 1 por semana
A31: Escenario comisión 3 | B31: 0.3 | E31: Monedero — mes de inicio | F31: =B46 -> 46296 | G31: Se compra a cuotas sin interés junto con la lavadora
A32: Préstamo mamá — monto | B32: 35000000 | C32: Fuente: Felipe | E32: ¿Se incluye el monedero? (1 = sí, 0 = no) | F32: =Mobiliario!B56 -> 1 | G32: Se elige en la hoja Mobiliario
A33: Préstamo mamá — tasa nominal mensual | B33: 0.015 | C33: Fuente: Felipe | E33: Inquilinos del estimado de gastos (columna C) | F33: 6 | G33: Los gastos se extrapolan por inquilino adicional
A34: Préstamo mamá — fecha de desembolso (para cálculo de intereses) | B34: 46249 | C34: Acordado: intereses desde el 15 ago, aunque hubo desembolsos parciales desde el 15 jul | E34: Cuota mensual promedio de muebles por habitación | F34: 850000 | G34: Felipe: desde el 2º mes ~850.000 por habitación
A35: Préstamo mamá — fecha primera cuota | B35: 46371 | C35: Fuente: Felipe | E35: Mes en que entra la venta de objetos (= compra muebles Hab 7) | F35: =G12 -> 46844
A36: Préstamo mamá — número de cuotas (sistema francés) | B36: 36 | C36: 3 años desde la primera cuota
A37: Préstamo mamá — tasa efectiva anual equivalente | B37: =(1+B33)^12-1 -> 0.19561817
A38: Cuenta de ahorros abuelos — rendimiento efectivo anual | B38: 0.085 | C38: Fuente: Felipe
A39: Cuenta de ahorros abuelos — saldo (ILUSTRATIVO) | B39: 100000000 | C39: Valor ilustrativo, no es el saldo real
A40: CDT 360 días — tasa promedio del mercado (EA) | B40: 0.1207 | C40: Banco de la República vía Infobae/El País, sep 2026
A41: CDT 360 días — tasa alta del mercado (EA) | B41: 0.13 | C41: KOA / Pibank, sep 2026 (finanzasplus.co)
A42: Rendimiento mensual equivalente de la cuenta de ahorros | B42: =(1+B38)^(1/12)-1 -> 0.0068214934
A43: Mobiliario — número de cuotas por habitación (derivado de la cuota promedio, celda F34) | B43: =ROUND(Mobiliario!B44/F34,0) -> 8 | C43: Cuotas sin interés de Mercado Libre
A44: Mobiliario — costo habitación pequeña vs. grande | B44: 1 | C44: Felipe: rango parecido
A45: Lavandería nueva — lavadora + monedero | B45: =Mobiliario!C57 -> 4020000 | C45: Se elige en la hoja Mobiliario
A46: Lavadora nueva — mes de compra | B46: 46296
A47: Lavadora nueva — ahorro mensual estimado (energía + agua) | B47: 45000 | C47: Estimado de Felipe: entre 40.000 y 50.000
A50: Ingreso neto de la casa ANTES de la remodelación (mensual) | B50: 620000 | C50: Felipe: bruto ~820.000, neto ~620.000
A52: Referencia de mercado: honorario de administración inmobiliaria (sobre canon bruto) | B52: 0.1 | C52: Bogotá 8%–12% + IVA (Inmobiliare Latam, guía 2026)
A53: IVA sobre honorarios | B53: 0.19
A54: Primer mes de la proyección | B54: 46296
A56: Listas (usadas en Movimientos)
A57: Categoría | B57: Grupo | D57: Fuente del dinero | F57: Estado del soporte
A58: Obra – contratista principal | B58: Obra y adecuaciones | D58: Abuelos – capital propio | F58: Soportado
A59: Costos bancarios – 4x1000 | B59: Obra y adecuaciones | D59: Préstamo mamá | F59: Por desglosar
A60: Eléctrico – aumento de carga (Enel) | B60: Obra y adecuaciones | D60: TC abuelos (cuotas) | F60: Pendiente de pago
A61: Seguridad – cámaras | B61: Obra y adecuaciones | D61: Arriendo de la casa
A62: Hidráulico – bomba de presión | B62: Obra y adecuaciones | D62: Felipe (por definir)
A63: Mobiliario – habitaciones | B63: Mobiliario | D63: Por confirmar
A64: Lavandería – lavadora | B64: Mobiliario
A65: Traslado entre cuentas | B65: Traslado (no es gasto)
